{
"meta":{"test_sets":[],"test_metrics":[],"learn_metrics":[{"best_value":"Min","name":"RMSE"}],"launch_mode":"Train","parameters":"","iteration_count":1000,"learn_sets":["learn"],"name":"experiment"},
"iterations":[
{"learn":[798740.214],"iteration":0,"passed_time":0.04732679299,"remaining_time":47.27946619},
{"learn":[770875.6269],"iteration":1,"passed_time":0.04805892188,"remaining_time":23.98140202},
{"learn":[744189.5954],"iteration":2,"passed_time":0.04873585622,"remaining_time":16.19654955},
{"learn":[718274.9825],"iteration":3,"passed_time":0.04948098513,"remaining_time":12.3207653},
{"learn":[695630.6449],"iteration":4,"passed_time":0.05017045362,"remaining_time":9.98392027},
{"learn":[673664.4752],"iteration":5,"passed_time":0.05088470393,"remaining_time":8.429899284},
{"learn":[653597.2613],"iteration":6,"passed_time":0.0516609334,"remaining_time":7.32847241},
{"learn":[634980.7758],"iteration":7,"passed_time":0.05233288377,"remaining_time":6.489277587},
{"learn":[617722.5325],"iteration":8,"passed_time":0.05302441744,"remaining_time":5.83857752},
{"learn":[601422.1335],"iteration":9,"passed_time":0.05372904661,"remaining_time":5.319175615},
{"learn":[585285.4042],"iteration":10,"passed_time":0.05454392476,"remaining_time":4.903994689},
{"learn":[570599.7898],"iteration":11,"passed_time":0.05542470492,"remaining_time":4.563300705},
{"learn":[556241.0109],"iteration":12,"passed_time":0.05615662754,"remaining_time":4.263583952},
{"learn":[542854.8859],"iteration":13,"passed_time":0.05683750707,"remaining_time":4.002984426},
{"learn":[530642.2487],"iteration":14,"passed_time":0.05755997555,"remaining_time":3.779771728},
{"learn":[519589.0203],"iteration":15,"passed_time":0.05843012843,"remaining_time":3.593452899},
{"learn":[509587.0553],"iteration":16,"passed_time":0.0591878973,"remaining_time":3.422453121},
{"learn":[500361.574],"iteration":17,"passed_time":0.05988647394,"remaining_time":3.267139856},
{"learn":[491637.0377],"iteration":18,"passed_time":0.06064212017,"remaining_time":3.131048415},
{"learn":[483388.9648],"iteration":19,"passed_time":0.06132604498,"remaining_time":3.004976204},
{"learn":[476097.0524],"iteration":20,"passed_time":0.06230928295,"remaining_time":2.904799429},
{"learn":[468789.6018],"iteration":21,"passed_time":0.0633341169,"remaining_time":2.815489379},
{"learn":[462356.6564],"iteration":22,"passed_time":0.06405013064,"remaining_time":2.720738158},
{"learn":[456089.0555],"iteration":23,"passed_time":0.06474754944,"remaining_time":2.63306701},
{"learn":[450251.4029],"iteration":24,"passed_time":0.06541725852,"remaining_time":2.551273082},
{"learn":[445308.5272],"iteration":25,"passed_time":0.06643198315,"remaining_time":2.488644292},
{"learn":[440593.2483],"iteration":26,"passed_time":0.06730648549,"remaining_time":2.42552631},
{"learn":[435746.8639],"iteration":27,"passed_time":0.06804414525,"remaining_time":2.362103899},
{"learn":[431469.0684],"iteration":28,"passed_time":0.06904758038,"remaining_time":2.311903467},
{"learn":[427932.0179],"iteration":29,"passed_time":0.06985339418,"remaining_time":2.258593079},
{"learn":[424270.1518],"iteration":30,"passed_time":0.07067494532,"remaining_time":2.209162001},
{"learn":[420843.8229],"iteration":31,"passed_time":0.07136430799,"remaining_time":2.158770317},
{"learn":[417906.3472],"iteration":32,"passed_time":0.07206437069,"remaining_time":2.111704438},
{"learn":[414896.736],"iteration":33,"passed_time":0.07280775187,"remaining_time":2.068596715},
{"learn":[412029.7139],"iteration":34,"passed_time":0.07368153619,"remaining_time":2.031505212},
{"learn":[409506.1879],"iteration":35,"passed_time":0.07443457448,"remaining_time":1.993192494},
{"learn":[407033.2723],"iteration":36,"passed_time":0.07514051072,"remaining_time":1.955684103},
{"learn":[404615.3681],"iteration":37,"passed_time":0.07584715548,"remaining_time":1.92013062},
{"learn":[402551.422],"iteration":38,"passed_time":0.07653821585,"remaining_time":1.885980139},
{"learn":[400744.3683],"iteration":39,"passed_time":0.07720789558,"remaining_time":1.852989494},
{"learn":[399026.4793],"iteration":40,"passed_time":0.07787970995,"remaining_time":1.821625411},
{"learn":[397300.6427],"iteration":41,"passed_time":0.07861014321,"remaining_time":1.793059933},
{"learn":[395620.7201],"iteration":42,"passed_time":0.07933881097,"remaining_time":1.765749816},
{"learn":[394252.6915],"iteration":43,"passed_time":0.07998177721,"remaining_time":1.737785887},
{"learn":[392794.5594],"iteration":44,"passed_time":0.08063009491,"remaining_time":1.711149792},
{"learn":[391386.4209],"iteration":45,"passed_time":0.08126195974,"remaining_time":1.685302382},
{"learn":[390337.2821],"iteration":46,"passed_time":0.08195588888,"remaining_time":1.661786428},
{"learn":[388974.5175],"iteration":47,"passed_time":0.08264571204,"remaining_time":1.639139955},
{"learn":[387743.4074],"iteration":48,"passed_time":0.08333536778,"remaining_time":1.617386424},
{"learn":[386964.5349],"iteration":49,"passed_time":0.08403691654,"remaining_time":1.596701414},
{"learn":[385896.5407],"iteration":50,"passed_time":0.08490222268,"remaining_time":1.579847242},
{"learn":[384915.6317],"iteration":51,"passed_time":0.08563211732,"remaining_time":1.56113937},
{"learn":[383832.587],"iteration":52,"passed_time":0.08637088449,"remaining_time":1.543268446},
{"learn":[382977.8782],"iteration":53,"passed_time":0.08715266095,"remaining_time":1.526785505},
{"learn":[382125.5954],"iteration":54,"passed_time":0.08787731698,"remaining_time":1.509892083},
{"learn":[381322.8013],"iteration":55,"passed_time":0.08877515849,"remaining_time":1.496495529},
{"learn":[380102.0915],"iteration":56,"passed_time":0.08944951176,"remaining_time":1.479840168},
{"learn":[379532.6448],"iteration":57,"passed_time":0.09018676849,"remaining_time":1.464757516},
{"learn":[378802.2151],"iteration":58,"passed_time":0.09088564936,"remaining_time":1.449549086},
{"learn":[378106.6118],"iteration":59,"passed_time":0.09178432712,"remaining_time":1.437954458},
{"learn":[377353.0461],"iteration":60,"passed_time":0.09250601889,"remaining_time":1.423986094},
{"learn":[376726.3448],"iteration":61,"passed_time":0.09317219078,"remaining_time":1.40960508},
{"learn":[375967.7957],"iteration":62,"passed_time":0.09384104006,"remaining_time":1.395699278},
{"learn":[375473.9403],"iteration":63,"passed_time":0.09447179293,"remaining_time":1.381649972},
{"learn":[374916.1637],"iteration":64,"passed_time":0.09514916337,"remaining_time":1.368684119},
{"learn":[374128.4198],"iteration":65,"passed_time":0.0959718922,"remaining_time":1.358147687},
{"learn":[373758.0051],"iteration":66,"passed_time":0.09666921551,"remaining_time":1.346154897},
{"learn":[372958.8864],"iteration":67,"passed_time":0.09732856517,"remaining_time":1.333973864},
{"learn":[372359.8559],"iteration":68,"passed_time":0.09799690353,"remaining_time":1.322248075},
{"learn":[371921.6497],"iteration":69,"passed_time":0.09887656967,"remaining_time":1.313645854},
{"learn":[371574.1386],"iteration":70,"passed_time":0.09956327934,"remaining_time":1.30273643},
{"learn":[371066.2631],"iteration":71,"passed_time":0.1003621837,"remaining_time":1.293557034},
{"learn":[370270.0843],"iteration":72,"passed_time":0.1010567407,"remaining_time":1.283282174},
{"learn":[369701.8967],"iteration":73,"passed_time":0.1018602153,"remaining_time":1.274629181},
{"learn":[369130.3037],"iteration":74,"passed_time":0.1025424275,"remaining_time":1.26468994},
{"learn":[368474.7858],"iteration":75,"passed_time":0.1032435017,"remaining_time":1.255223626},
{"learn":[367961.6337],"iteration":76,"passed_time":0.1039458483,"remaining_time":1.246000233},
{"learn":[367080.0235],"iteration":77,"passed_time":0.1047577208,"remaining_time":1.238289982},
{"learn":[366725.347],"iteration":78,"passed_time":0.1055346617,"remaining_time":1.230347132},
{"learn":[366218.2898],"iteration":79,"passed_time":0.1062477732,"remaining_time":1.221849392},
{"learn":[365894.9834],"iteration":80,"passed_time":0.1069333759,"remaining_time":1.213231758},
{"learn":[365538.2315],"iteration":81,"passed_time":0.1076083992,"remaining_time":1.204689152},
{"learn":[365185.6782],"iteration":82,"passed_time":0.1082602479,"remaining_time":1.196080088},
{"learn":[364748.0975],"iteration":83,"passed_time":0.1089279092,"remaining_time":1.187832914},
{"learn":[364389.6259],"iteration":84,"passed_time":0.1096674266,"remaining_time":1.180537592},
{"learn":[364011.1086],"iteration":85,"passed_time":0.1103591145,"remaining_time":1.172886402},
{"learn":[363696.7328],"iteration":86,"passed_time":0.1110121706,"remaining_time":1.16498979},
{"learn":[363288.381],"iteration":87,"passed_time":0.111660022,"remaining_time":1.157203865},
{"learn":[362842.1243],"iteration":88,"passed_time":0.1123796953,"remaining_time":1.15031351},
{"learn":[362353.9444],"iteration":89,"passed_time":0.1130516047,"remaining_time":1.143077337},
{"learn":[361865.3465],"iteration":90,"passed_time":0.113694213,"remaining_time":1.135692743},
{"learn":[361354.8864],"iteration":91,"passed_time":0.1143703789,"remaining_time":1.128785914},
{"learn":[361077.4179],"iteration":92,"passed_time":0.1150457375,"remaining_time":1.122005203},
{"learn":[360778.7717],"iteration":93,"passed_time":0.1157292568,"remaining_time":1.115433049},
{"learn":[360512.5466],"iteration":94,"passed_time":0.1164486072,"remaining_time":1.109326206},
{"learn":[360231.4421],"iteration":95,"passed_time":0.1171086733,"remaining_time":1.10277334},
{"learn":[359774.7001],"iteration":96,"passed_time":0.1177730383,"remaining_time":1.096381996},
{"learn":[359579.2383],"iteration":97,"passed_time":0.1183229988,"remaining_time":1.08905454},
{"learn":[359297.9519],"iteration":98,"passed_time":0.1191134891,"remaining_time":1.084053067},
{"learn":[358988.9638],"iteration":99,"passed_time":0.1198314973,"remaining_time":1.078483476},
{"learn":[358871.9258],"iteration":100,"passed_time":0.1203973035,"remaining_time":1.071655206},
{"learn":[358470.0306],"iteration":101,"passed_time":0.1210845476,"remaining_time":1.06601886},
{"learn":[357708.8018],"iteration":102,"passed_time":0.1218299866,"remaining_time":1.060985417},
{"learn":[357227.2037],"iteration":103,"passed_time":0.1228587831,"remaining_time":1.058475669},
{"learn":[357035.7256],"iteration":104,"passed_time":0.1244166216,"remaining_time":1.060503584},
{"learn":[356876.7347],"iteration":105,"passed_time":0.1250928784,"remaining_time":1.055028616},
{"learn":[356791.86],"iteration":106,"passed_time":0.1255737263,"remaining_time":1.0480125},
{"learn":[356413.9855],"iteration":107,"passed_time":0.1262576039,"remaining_time":1.042794284},
{"learn":[355757.3561],"iteration":108,"passed_time":0.126960225,"remaining_time":1.037812481},
{"learn":[355643.2809],"iteration":109,"passed_time":0.1276752611,"remaining_time":1.033008931},
{"learn":[355056.4379],"iteration":110,"passed_time":0.1283384654,"remaining_time":1.027863926},
{"learn":[354646.1945],"iteration":111,"passed_time":0.1290205102,"remaining_time":1.022948331},
{"learn":[354437.0267],"iteration":112,"passed_time":0.1300809645,"remaining_time":1.021078014},
{"learn":[354164.855],"iteration":113,"passed_time":0.1309059508,"remaining_time":1.017391863},
{"learn":[353928.4739],"iteration":114,"passed_time":0.1317196152,"remaining_time":1.013668343},
{"learn":[353853.0938],"iteration":115,"passed_time":0.1323326102,"remaining_time":1.008465754},
{"learn":[353640.2184],"iteration":116,"passed_time":0.1331042687,"remaining_time":1.004539053},
{"learn":[353298.9969],"iteration":117,"passed_time":0.1338981362,"remaining_time":1.000831831},
{"learn":[353072.0535],"iteration":118,"passed_time":0.1346345587,"remaining_time":0.9967482876},
{"learn":[352694.9676],"iteration":119,"passed_time":0.1353229367,"remaining_time":0.9923682027},
{"learn":[352573.8267],"iteration":120,"passed_time":0.1360010533,"remaining_time":0.9879745939},
{"learn":[352349.832],"iteration":121,"passed_time":0.1367741937,"remaining_time":0.9843257545},
{"learn":[352011.5453],"iteration":122,"passed_time":0.1375732299,"remaining_time":0.980908314},
{"learn":[351974.5803],"iteration":123,"passed_time":0.1383941176,"remaining_time":0.9776874759},
{"learn":[351810.5082],"iteration":124,"passed_time":0.1390477905,"remaining_time":0.9733345333},
{"learn":[351775.8735],"iteration":125,"passed_time":0.1395047395,"remaining_time":0.9676757324},
{"learn":[351586.1886],"iteration":126,"passed_time":0.1401711614,"remaining_time":0.9635387712},
{"learn":[351536.1053],"iteration":127,"passed_time":0.1408531509,"remaining_time":0.9595620902},
{"learn":[351014.3286],"iteration":128,"passed_time":0.141539801,"remaining_time":0.9556679587},
{"learn":[350896.5477],"iteration":129,"passed_time":0.1422695844,"remaining_time":0.9521118344},
{"learn":[350370.2771],"iteration":130,"passed_time":0.1429709906,"remaining_time":0.948410617},
{"learn":[350070.8564],"iteration":131,"passed_time":0.1436304597,"remaining_time":0.9444790836},
{"learn":[349980.858],"iteration":132,"passed_time":0.1442735405,"remaining_time":0.9404899217},
{"learn":[349956.2556],"iteration":133,"passed_time":0.1447382219,"remaining_time":0.9353977625},
{"learn":[349716.9155],"iteration":134,"passed_time":0.145404221,"remaining_time":0.9316640828},
{"learn":[349203.1676],"iteration":135,"passed_time":0.1461081181,"remaining_time":0.9282162798},
{"learn":[349175.5632],"iteration":136,"passed_time":0.1465181329,"remaining_time":0.9229572896},
{"learn":[349050.7576],"iteration":137,"passed_time":0.1472023293,"remaining_time":0.9194812162},
{"learn":[348847.5886],"iteration":138,"passed_time":0.1478918846,"remaining_time":0.916078508},
{"learn":[348652.5351],"iteration":139,"passed_time":0.1486234314,"remaining_time":0.9129725074},
{"learn":[348246.9244],"iteration":140,"passed_time":0.1494292734,"remaining_time":0.9103528072},
{"learn":[348221.6212],"iteration":141,"passed_time":0.1499041332,"remaining_time":0.9057587764},
{"learn":[347984.7515],"iteration":142,"passed_time":0.1506546731,"remaining_time":0.9028745091},
{"learn":[347670.2306],"iteration":143,"passed_time":0.1513555137,"remaining_time":0.8997244426},
{"learn":[347394.7441],"iteration":144,"passed_time":0.1521128717,"remaining_time":0.8969414158},
{"learn":[346839.2557],"iteration":145,"passed_time":0.1528573619,"remaining_time":0.8941108705},
{"learn":[346537.1056],"iteration":146,"passed_time":0.1535602492,"remaining_time":0.8910672963},
{"learn":[346467.3312],"iteration":147,"passed_time":0.155428649,"remaining_time":0.8947649254},
{"learn":[346126.3008],"iteration":148,"passed_time":0.1561792906,"remaining_time":0.8920038678},
{"learn":[346057.3762],"iteration":149,"passed_time":0.1568283668,"remaining_time":0.8886940787},
{"learn":[346013.3098],"iteration":150,"passed_time":0.1574423155,"remaining_time":0.8852220253},
{"learn":[345471.3897],"iteration":151,"passed_time":0.1580872626,"remaining_time":0.8819605175},
{"learn":[345123.1907],"iteration":152,"passed_time":0.1587876535,"remaining_time":0.879040147},
{"learn":[344608.3831],"iteration":153,"passed_time":0.1594577077,"remaining_time":0.8759819528},
{"learn":[344571.9003],"iteration":154,"passed_time":0.1600817028,"remaining_time":0.8727034768},
{"learn":[344460.0604],"iteration":155,"passed_time":0.1608951061,"remaining_time":0.8704837791},
{"learn":[344421.4852],"iteration":156,"passed_time":0.1614255155,"remaining_time":0.8667624815},
{"learn":[344380.0071],"iteration":157,"passed_time":0.1622695411,"remaining_time":0.8647528708},
{"learn":[344182.4029],"iteration":158,"passed_time":0.1639773722,"remaining_time":0.8673268557},
{"learn":[343970.0544],"iteration":159,"passed_time":0.1647476901,"remaining_time":0.8649253732},
{"learn":[343801.4134],"iteration":160,"passed_time":0.1655507001,"remaining_time":0.8627145178},
{"learn":[343471.9852],"iteration":161,"passed_time":0.1663126683,"remaining_time":0.8603087412},
{"learn":[343074.7708],"iteration":162,"passed_time":0.1669875995,"remaining_time":0.8574762012},
{"learn":[342663.2516],"iteration":163,"passed_time":0.1676230321,"remaining_time":0.8544686271},
{"learn":[342214.5894],"iteration":164,"passed_time":0.1683858978,"remaining_time":0.852134695},
{"learn":[342138.8603],"iteration":165,"passed_time":0.1690585302,"remaining_time":0.8493663507},
{"learn":[341973.2276],"iteration":166,"passed_time":0.1699525316,"remaining_time":0.8477272982},
{"learn":[341494.8999],"iteration":167,"passed_time":0.1706544986,"remaining_time":0.8451460885},
{"learn":[341423.645],"iteration":168,"passed_time":0.171662821,"remaining_time":0.8440935164},
{"learn":[341066.0851],"iteration":169,"passed_time":0.1723076871,"remaining_time":0.8412669429},
{"learn":[340703.4807],"iteration":170,"passed_time":0.1729762942,"remaining_time":0.8385809816},
{"learn":[340282.8084],"iteration":171,"passed_time":0.1736404434,"remaining_time":0.8358970184},
{"learn":[339965.3703],"iteration":172,"passed_time":0.1743047581,"remaining_time":0.8332371961},
{"learn":[339735.6146],"iteration":173,"passed_time":0.1749345255,"remaining_time":0.8304363105},
{"learn":[339407.6823],"iteration":174,"passed_time":0.1757434958,"remaining_time":0.8285050514},
{"learn":[339373.621],"iteration":175,"passed_time":0.1763607885,"remaining_time":0.8256891463},
{"learn":[338932.8637],"iteration":176,"passed_time":0.1770059779,"remaining_time":0.8230277954},
{"learn":[338737.6982],"iteration":177,"passed_time":0.1777216287,"remaining_time":0.8207144875},
{"learn":[338585.8029],"iteration":178,"passed_time":0.178247222,"remaining_time":0.8175473141},
{"learn":[338216.1066],"iteration":179,"passed_time":0.1789796505,"remaining_time":0.8153517414},
{"learn":[338183.4098],"iteration":180,"passed_time":0.1796052739,"remaining_time":0.8126890572},
{"learn":[338152.3624],"iteration":181,"passed_time":0.1802331436,"remaining_time":0.810058854},
{"learn":[338127.8813],"iteration":182,"passed_time":0.180895944,"remaining_time":0.8076064823},
{"learn":[338097.5071],"iteration":183,"passed_time":0.1815241427,"remaining_time":0.8050201111},
{"learn":[337954.7063],"iteration":184,"passed_time":0.1822360008,"remaining_time":0.8028234632},
{"learn":[337618.8362],"iteration":185,"passed_time":0.1828993854,"remaining_time":0.8004306436},
{"learn":[337183.4855],"iteration":186,"passed_time":0.1836520277,"remaining_time":0.798444377},
{"learn":[336783.009],"iteration":187,"passed_time":0.1843689674,"remaining_time":0.7963170292},
{"learn":[336749.9354],"iteration":188,"passed_time":0.1850555452,"remaining_time":0.7940743234},
{"learn":[336424.6499],"iteration":189,"passed_time":0.1859529134,"remaining_time":0.7927466307},
{"learn":[335953.6553],"iteration":190,"passed_time":0.1867089709,"remaining_time":0.7908249082},
{"learn":[335931.9937],"iteration":191,"passed_time":0.1873676803,"remaining_time":0.7885056544},
{"learn":[335585.4403],"iteration":192,"passed_time":0.188093397,"remaining_time":0.7864837895},
{"learn":[335192.3489],"iteration":193,"passed_time":0.1887669033,"remaining_time":0.7842583713},
{"learn":[335041.0152],"iteration":194,"passed_time":0.1894086038,"remaining_time":0.7819175695},
{"learn":[335013.7106],"iteration":195,"passed_time":0.1900652389,"remaining_time":0.7796553676},
{"learn":[334742.1494],"iteration":196,"passed_time":0.1907703587,"remaining_time":0.7776070966},
{"learn":[334585.0608],"iteration":197,"passed_time":0.1918357705,"remaining_time":0.7770317573},
{"learn":[334166.9185],"iteration":198,"passed_time":0.192675936,"remaining_time":0.775544848},
{"learn":[334027.4769],"iteration":199,"passed_time":0.1933928319,"remaining_time":0.7735713276},
{"learn":[333915.8883],"iteration":200,"passed_time":0.1940876771,"remaining_time":0.7715226566},
{"learn":[333445.4205],"iteration":201,"passed_time":0.1948545177,"remaining_time":0.7697718076},
{"learn":[333417.0084],"iteration":202,"passed_time":0.1955850196,"remaining_time":0.7678879833},
{"learn":[332992.7283],"iteration":203,"passed_time":0.1963274823,"remaining_time":0.7660621367},
{"learn":[332695.5523],"iteration":204,"passed_time":0.197179213,"remaining_time":0.7646706065},
{"learn":[332207.9762],"iteration":205,"passed_time":0.1979318073,"remaining_time":0.7629022088},
{"learn":[331676.1392],"iteration":206,"passed_time":0.1987011749,"remaining_time":0.7612078825},
{"learn":[331204.1695],"iteration":207,"passed_time":0.1994139825,"remaining_time":0.7593070874},
{"learn":[330833.3995],"iteration":208,"passed_time":0.2002838473,"remaining_time":0.7580120728},
{"learn":[330452.1865],"iteration":209,"passed_time":0.2011398932,"remaining_time":0.756669122},
{"learn":[330344.2297],"iteration":210,"passed_time":0.2019940049,"remaining_time":0.7553235539},
{"learn":[330321.5119],"iteration":211,"passed_time":0.2027473065,"remaining_time":0.7536079129},
{"learn":[330058.1664],"iteration":212,"passed_time":0.2034809789,"remaining_time":0.7518287813},
{"learn":[329824.9457],"iteration":213,"passed_time":0.2043132983,"remaining_time":0.7504217405},
{"learn":[329594.7542],"iteration":214,"passed_time":0.2050362318,"remaining_time":0.7486206604},
{"learn":[329474.8931],"iteration":215,"passed_time":0.205745993,"remaining_time":0.7467817522},
{"learn":[329347.4616],"iteration":216,"passed_time":0.2064687128,"remaining_time":0.7450000097},
{"learn":[329293.8218],"iteration":217,"passed_time":0.2071809277,"remaining_time":0.7431903001},
{"learn":[329091.8479],"iteration":218,"passed_time":0.2079093052,"remaining_time":0.7414482529},
{"learn":[328803.7988],"iteration":219,"passed_time":0.2086160649,"remaining_time":0.7396387756},
{"learn":[328418.2235],"iteration":220,"passed_time":0.2093208069,"remaining_time":0.7378321656},
{"learn":[328341.9399],"iteration":221,"passed_time":0.2100379599,"remaining_time":0.7360789766},
{"learn":[328010.9471],"iteration":222,"passed_time":0.2107855537,"remaining_time":0.7344411446},
{"learn":[327710.814],"iteration":223,"passed_time":0.2115080354,"remaining_time":0.7327242656},
{"learn":[327431.7035],"iteration":224,"passed_time":0.2123165419,"remaining_time":0.7313125333},
{"learn":[327160.5889],"iteration":225,"passed_time":0.2131291705,"remaining_time":0.7299202565},
{"learn":[326881.27],"iteration":226,"passed_time":0.2138861569,"remaining_time":0.7283436091},
{"learn":[326527.8563],"iteration":227,"passed_time":0.2146460149,"remaining_time":0.7267838751},
{"learn":[326503.6995],"iteration":228,"passed_time":0.216060721,"remaining_time":0.7274358774},
{"learn":[326480.113],"iteration":229,"passed_time":0.2167294322,"remaining_time":0.7255724471},
{"learn":[326306.8001],"iteration":230,"passed_time":0.2174112894,"remaining_time":0.7237631236},
{"learn":[326063.7375],"iteration":231,"passed_time":0.2180796009,"remaining_time":0.7219186788},
{"learn":[325809.9707],"iteration":232,"passed_time":0.2187595648,"remaining_time":0.7201226875},
{"learn":[325486.6685],"iteration":233,"passed_time":0.2194382022,"remaining_time":0.7183318927},
{"learn":[325455.9921],"iteration":234,"passed_time":0.2201454451,"remaining_time":0.716643683},
{"learn":[325287.6907],"iteration":235,"passed_time":0.2209776661,"remaining_time":0.7153683767},
{"learn":[325050.5992],"iteration":236,"passed_time":0.2218079406,"remaining_time":0.7140905428},
{"learn":[324719.9076],"iteration":237,"passed_time":0.2224961185,"remaining_time":0.7123615223},
{"learn":[324657.1207],"iteration":238,"passed_time":0.2231227976,"remaining_time":0.7104453933},
{"learn":[324634.9908],"iteration":239,"passed_time":0.2237733331,"remaining_time":0.7086155547},
{"learn":[324329.0549],"iteration":240,"passed_time":0.2244432273,"remaining_time":0.7068564711},
{"learn":[324044.1769],"iteration":241,"passed_time":0.2251273034,"remaining_time":0.7051508099},
{"learn":[323731.026],"iteration":242,"passed_time":0.2258433569,"remaining_time":0.7035531734},
{"learn":[323713.4629],"iteration":243,"passed_time":0.2265134694,"remaining_time":0.7018204216},
{"learn":[323525.8143],"iteration":244,"passed_time":0.2273529971,"remaining_time":0.7006184196},
{"learn":[323197.0228],"iteration":245,"passed_time":0.2281071469,"remaining_time":0.6991576779},
{"learn":[322951.8806],"iteration":246,"passed_time":0.2289510811,"remaining_time":0.6979763728},
{"learn":[322712.9394],"iteration":247,"passed_time":0.2297206119,"remaining_time":0.6965721782},
{"learn":[322441.8203],"iteration":248,"passed_time":0.230453277,"remaining_time":0.6950618916},
{"learn":[322386.0222],"iteration":249,"passed_time":0.2311055891,"remaining_time":0.6933167672},
{"learn":[322199.649],"iteration":250,"passed_time":0.2318833331,"remaining_time":0.6919546474},
{"learn":[321989.2058],"iteration":251,"passed_time":0.2325963454,"remaining_time":0.6904050252},
{"learn":[321788.3926],"iteration":252,"passed_time":0.2332990392,"remaining_time":0.6888315504},
{"learn":[321472.559],"iteration":253,"passed_time":0.2340293377,"remaining_time":0.6873460075},
{"learn":[321372.144],"iteration":254,"passed_time":0.2347046045,"remaining_time":0.6857056092},
{"learn":[321200.8761],"iteration":255,"passed_time":0.2354653798,"remaining_time":0.68432126},
{"learn":[320979.1305],"iteration":256,"passed_time":0.2361524396,"remaining_time":0.6827286483},
{"learn":[320697.0614],"iteration":257,"passed_time":0.2368627488,"remaining_time":0.6812099211},
{"learn":[320395.8204],"iteration":258,"passed_time":0.23753241,"remaining_time":0.679581142},
{"learn":[320166.2071],"iteration":259,"passed_time":0.2381991383,"remaining_time":0.6779513935},
{"learn":[320079.4726],"iteration":260,"passed_time":0.2388740492,"remaining_time":0.6763521928},
{"learn":[319777.8874],"iteration":261,"passed_time":0.2395101738,"remaining_time":0.6746507948},
{"learn":[319466.4271],"iteration":262,"passed_time":0.2402351762,"remaining_time":0.6732065583},
{"learn":[319374.9153],"iteration":263,"passed_time":0.2408719774,"remaining_time":0.6715218765},
{"learn":[319192.8664],"iteration":264,"passed_time":0.2415438055,"remaining_time":0.6699422529},
{"learn":[319156.9148],"iteration":265,"passed_time":0.2422074765,"remaining_time":0.6683469464},
{"learn":[319069.7393],"iteration":266,"passed_time":0.2428717833,"remaining_time":0.6667603638},
{"learn":[318798.3345],"iteration":267,"passed_time":0.2436627088,"remaining_time":0.6655265031},
{"learn":[318574.5203],"iteration":268,"passed_time":0.2444975489,"remaining_time":0.6644152722},
{"learn":[318296.5185],"iteration":269,"passed_time":0.2455449874,"remaining_time":0.663880892},
{"learn":[318111.6701],"iteration":270,"passed_time":0.2462800508,"remaining_time":0.6625024246},
{"learn":[317901.6451],"iteration":271,"passed_time":0.2469438814,"remaining_time":0.6609380356},
{"learn":[317697.6858],"iteration":272,"passed_time":0.247636854,"remaining_time":0.6594578494},
{"learn":[317390.7247],"iteration":273,"passed_time":0.2484244147,"remaining_time":0.6582340332},
{"learn":[317158.8194],"iteration":274,"passed_time":0.2492364005,"remaining_time":0.6570777833},
{"learn":[317140.665],"iteration":275,"passed_time":0.2499649592,"remaining_time":0.6557051828},
{"learn":[316974.0001],"iteration":276,"passed_time":0.2506382522,"remaining_time":0.6541929831},
{"learn":[316715.34],"iteration":277,"passed_time":0.2513204425,"remaining_time":0.6527099262},
{"learn":[316466.6966],"iteration":278,"passed_time":0.2519962769,"remaining_time":0.651216185},
{"learn":[316231.6686],"iteration":279,"passed_time":0.2526685695,"remaining_time":0.6497191787},
{"learn":[316049.4414],"iteration":280,"passed_time":0.2533401586,"remaining_time":0.648226242},
{"learn":[315743.8727],"iteration":281,"passed_time":0.2540609314,"remaining_time":0.6468643573},
{"learn":[315478.2384],"iteration":282,"passed_time":0.2547172205,"remaining_time":0.6453436293},
{"learn":[315294.9237],"iteration":283,"passed_time":0.2553906859,"remaining_time":0.6438722925},
{"learn":[315049.5947],"iteration":284,"passed_time":0.2560748058,"remaining_time":0.6424332847},
{"learn":[315032.2123],"iteration":285,"passed_time":0.2567018082,"remaining_time":0.6408569617},
{"learn":[315017.8998],"iteration":286,"passed_time":0.25758316,"remaining_time":0.6399191397},
{"learn":[314636.1567],"iteration":287,"passed_time":0.2582495208,"remaining_time":0.6384502043},
{"learn":[314399.7682],"iteration":288,"passed_time":0.2589625546,"remaining_time":0.6371016482},
{"learn":[314385.3903],"iteration":289,"passed_time":0.2596799283,"remaining_time":0.6357681004},
{"learn":[314371.5953],"iteration":290,"passed_time":0.2603377605,"remaining_time":0.6342937189},
{"learn":[314358.1745],"iteration":291,"passed_time":0.262908194,"remaining_time":0.6374623333},
{"learn":[314088.8556],"iteration":292,"passed_time":0.2636738309,"remaining_time":0.6362368548},
{"learn":[313806.6949],"iteration":293,"passed_time":0.2650155701,"remaining_time":0.6363979337},
{"learn":[313765.4962],"iteration":294,"passed_time":0.2659336559,"remaining_time":0.6355363642},
{"learn":[313372.5064],"iteration":295,"passed_time":0.2666550976,"remaining_time":0.6342067186},
{"learn":[313201.4142],"iteration":296,"passed_time":0.2673635517,"remaining_time":0.632850427},
{"learn":[313039.1308],"iteration":297,"passed_time":0.2681023416,"remaining_time":0.6315699456},
{"learn":[312836.0723],"iteration":298,"passed_time":0.2687895361,"remaining_time":0.6301721231},
{"learn":[312600.6922],"iteration":299,"passed_time":0.2694756369,"remaining_time":0.6287764861},
{"learn":[312473.5394],"iteration":300,"passed_time":0.2701972398,"remaining_time":0.6274680087},
{"learn":[312398.1332],"iteration":301,"passed_time":0.2708899805,"remaining_time":0.6260967099},
{"learn":[312143.9437],"iteration":302,"passed_time":0.2715564008,"remaining_time":0.6246693445},
{"learn":[311908.148],"iteration":303,"passed_time":0.2723030935,"remaining_time":0.6234307667},
{"learn":[311656.4638],"iteration":304,"passed_time":0.2731227208,"remaining_time":0.6223616098},
{"learn":[311644.2332],"iteration":305,"passed_time":0.2738387048,"remaining_time":0.6210590233},
{"learn":[311632.4225],"iteration":306,"passed_time":0.2746151629,"remaining_time":0.6198967683},
{"learn":[311620.7243],"iteration":307,"passed_time":0.2755062719,"remaining_time":0.6189946108},
{"learn":[311593.9182],"iteration":308,"passed_time":0.2763403559,"remaining_time":0.617965003},
{"learn":[311387.8086],"iteration":309,"passed_time":0.276990676,"remaining_time":0.6165276336},
{"learn":[311120.8067],"iteration":310,"passed_time":0.2776104312,"remaining_time":0.6150276112},
{"learn":[311015.4306],"iteration":311,"passed_time":0.2783391895,"remaining_time":0.6137735973},
{"learn":[311004.5146],"iteration":312,"passed_time":0.2789818031,"remaining_time":0.6123338618},
{"learn":[310785.9875],"iteration":313,"passed_time":0.2798118775,"remaining_time":0.6113087514},
{"learn":[310508.9715],"iteration":314,"passed_time":0.2805950205,"remaining_time":0.6101828224},
{"learn":[310313.4421],"iteration":315,"passed_time":0.2818108293,"remaining_time":0.6099955925},
{"learn":[310233.3336],"iteration":316,"passed_time":0.2824853404,"remaining_time":0.6086356073},
{"learn":[310222.8457],"iteration":317,"passed_time":0.2831142088,"remaining_time":0.6071820452},
{"learn":[310043.361],"iteration":318,"passed_time":0.2838135187,"remaining_time":0.6058840321},
{"learn":[309928.1252],"iteration":319,"passed_time":0.284471985,"remaining_time":0.6045029682},
{"learn":[309918.1272],"iteration":320,"passed_time":0.2850973637,"remaining_time":0.6030564173},
{"learn":[309908.1943],"iteration":321,"passed_time":0.2857068165,"remaining_time":0.6015814336},
{"learn":[309705.752],"iteration":322,"passed_time":0.2863766897,"remaining_time":0.6002384488},
{"learn":[309664.4837],"iteration":323,"passed_time":0.2870150833,"remaining_time":0.5988339392},
{"learn":[309399.3424],"iteration":324,"passed_time":0.2876897168,"remaining_time":0.5975094119},
{"learn":[309154.0587],"iteration":325,"passed_time":0.2883758461,"remaining_time":0.5962126389},
{"learn":[308962.6358],"iteration":326,"passed_time":0.2892063281,"remaining_time":0.5952166936},
{"learn":[308785.9359],"iteration":327,"passed_time":0.28994685,"remaining_time":0.5940374488},
{"learn":[308550.9576],"iteration":328,"passed_time":0.290708216,"remaining_time":0.5929033828},
{"learn":[308297.0378],"iteration":329,"passed_time":0.2915170912,"remaining_time":0.5918680337},
{"learn":[308272.4772],"iteration":330,"passed_time":0.2922592592,"remaining_time":0.5906992277},
{"learn":[307997.8613],"iteration":331,"passed_time":0.2929920862,"remaining_time":0.5895141976},
{"learn":[307812.846],"iteration":332,"passed_time":0.2937372432,"remaining_time":0.5883565803},
{"learn":[307724.1083],"iteration":333,"passed_time":0.294402991,"remaining_time":0.5870430899},
{"learn":[307472.5284],"iteration":334,"passed_time":0.2951055343,"remaining_time":0.5858065085},
{"learn":[307448.9026],"iteration":335,"passed_time":0.2958231106,"remaining_time":0.5846028138},
{"learn":[307196.4616],"iteration":336,"passed_time":0.2965873731,"remaining_time":0.5834938527},
{"learn":[306988.9567],"iteration":337,"passed_time":0.2974344117,"remaining_time":0.5825490548},
{"learn":[306790.9183],"iteration":338,"passed_time":0.298196098,"remaining_time":0.5814384094},
{"learn":[306525.5577],"iteration":339,"passed_time":0.2988613985,"remaining_time":0.5801427148},
{"learn":[306502.4419],"iteration":340,"passed_time":0.2995093897,"remaining_time":0.5788172663},
{"learn":[306306.3432],"iteration":341,"passed_time":0.3001684612,"remaining_time":0.5775170978},
{"learn":[306283.825],"iteration":342,"passed_time":0.3008316514,"remaining_time":0.5762285568},
{"learn":[306261.9816],"iteration":343,"passed_time":0.3014751067,"remaining_time":0.5749060174},
{"learn":[306014.1238],"iteration":344,"passed_time":0.3021440159,"remaining_time":0.5736357403},
{"learn":[305928.8173],"iteration":345,"passed_time":0.3028188148,"remaining_time":0.5723800719},
{"learn":[305907.8841],"iteration":346,"passed_time":0.3034503084,"remaining_time":0.5710462576},
{"learn":[305720.3562],"iteration":347,"passed_time":0.3041361951,"remaining_time":0.5698183884},
{"learn":[305537.5086],"iteration":348,"passed_time":0.305122117,"remaining_time":0.5691532899},
{"learn":[305256.7234],"iteration":349,"passed_time":0.3058705334,"remaining_time":0.5680452764},
{"learn":[305107.3783],"iteration":350,"passed_time":0.3066347203,"remaining_time":0.5669684714},
{"learn":[304881.6269],"iteration":351,"passed_time":0.3077729444,"remaining_time":0.5665820112},
{"learn":[304732.1664],"iteration":352,"passed_time":0.3085627989,"remaining_time":0.5655527787},
{"learn":[304517.3701],"iteration":353,"passed_time":0.3093610472,"remaining_time":0.5645402161},
{"learn":[304365.3566],"iteration":354,"passed_time":0.3101594973,"remaining_time":0.5635292275},
{"learn":[304216.3883],"iteration":355,"passed_time":0.3108995575,"remaining_time":0.5624138062},
{"learn":[304161.5147],"iteration":356,"passed_time":0.3117849421,"remaining_time":0.5615622347},
{"learn":[303924.1508],"iteration":357,"passed_time":0.3126155684,"remaining_time":0.5606122762},
{"learn":[303865.0961],"iteration":358,"passed_time":0.3133595423,"remaining_time":0.5595082636},
{"learn":[303735.7257],"iteration":359,"passed_time":0.3140368851,"remaining_time":0.5582877957},
{"learn":[303515.2596],"iteration":360,"passed_time":0.3147178613,"remaining_time":0.5570767684},
{"learn":[303415.6859],"iteration":361,"passed_time":0.3153881421,"remaining_time":0.5558498195},
{"learn":[303322.9978],"iteration":362,"passed_time":0.3160584568,"remaining_time":0.5546259971},
{"learn":[303105.8583],"iteration":363,"passed_time":0.3167828032,"remaining_time":0.5534996231},
{"learn":[303056.4054],"iteration":364,"passed_time":0.3174182866,"remaining_time":0.5522208548},
{"learn":[302835.9689],"iteration":365,"passed_time":0.3180974296,"remaining_time":0.5510212305},
{"learn":[302620.6099],"iteration":366,"passed_time":0.3187688256,"remaining_time":0.5498110807},
{"learn":[302444.4847],"iteration":367,"passed_time":0.3194459402,"remaining_time":0.5486136799},
{"learn":[302237.8913],"iteration":368,"passed_time":0.3201400669,"remaining_time":0.5474481903},
{"learn":[301934.3948],"iteration":369,"passed_time":0.321001549,"remaining_time":0.5465702051},
{"learn":[301892.7826],"iteration":370,"passed_time":0.3217831944,"remaining_time":0.5455569523},
{"learn":[301789.1041],"iteration":371,"passed_time":0.3226474329,"remaining_time":0.5446843759},
{"learn":[301516.8396],"iteration":372,"passed_time":0.3234134897,"remaining_time":0.5436468045},
{"learn":[301403.007],"iteration":373,"passed_time":0.3242542567,"remaining_time":0.5427357345},
{"learn":[301224.6377],"iteration":374,"passed_time":0.325030869,"remaining_time":0.5417181149},
{"learn":[301093.0401],"iteration":375,"passed_time":0.32571521,"remaining_time":0.5405486464},
{"learn":[301016.443],"iteration":376,"passed_time":0.3263901536,"remaining_time":0.539366222},
{"learn":[300885.0819],"iteration":377,"passed_time":0.3272167106,"remaining_time":0.538435963},
{"learn":[300653.209],"iteration":378,"passed_time":0.3279832164,"remaining_time":0.537407856},
{"learn":[300555.1711],"iteration":379,"passed_time":0.3287059689,"remaining_time":0.5363097388},
{"learn":[300389.6423],"iteration":380,"passed_time":0.3293864061,"remaining_time":0.5351448436},
{"learn":[300211.1341],"iteration":381,"passed_time":0.3300821599,"remaining_time":0.5340072639},
{"learn":[300053.6021],"iteration":382,"passed_time":0.3307567004,"remaining_time":0.5328378176},
{"learn":[299862.5198],"iteration":383,"passed_time":0.3314361629,"remaining_time":0.5316788447},
{"learn":[299734.2731],"iteration":384,"passed_time":0.3322034078,"remaining_time":0.5306625865},
{"learn":[299675.5074],"iteration":385,"passed_time":0.3329089353,"remaining_time":0.5295494462},
{"learn":[299636.2281],"iteration":386,"passed_time":0.3335652281,"remaining_time":0.5283604259},
{"learn":[299586.9038],"iteration":387,"passed_time":0.3342746936,"remaining_time":0.5272580219},
{"learn":[299565.6285],"iteration":388,"passed_time":0.3348968162,"remaining_time":0.5260204491},
{"learn":[299391.9753],"iteration":389,"passed_time":0.3358181862,"remaining_time":0.5252540861},
{"learn":[299221.9361],"iteration":390,"passed_time":0.3365021433,"remaining_time":0.524117149},
{"learn":[299149.7242],"iteration":391,"passed_time":0.3371710409,"remaining_time":0.5229591655},
{"learn":[299027.01],"iteration":392,"passed_time":0.3378374257,"remaining_time":0.5217997898},
{"learn":[298898.4521],"iteration":393,"passed_time":0.3384967878,"remaining_time":0.5206321152},
{"learn":[298730.4008],"iteration":394,"passed_time":0.3391840084,"remaining_time":0.5195096837},
{"learn":[298585.1314],"iteration":395,"passed_time":0.3398773435,"remaining_time":0.5183987764},
{"learn":[298536.9411],"iteration":396,"passed_time":0.3406362322,"remaining_time":0.5173895416},
{"learn":[298358.3221],"iteration":397,"passed_time":0.341291955,"remaining_time":0.5162255198},
{"learn":[298206.7653],"iteration":398,"passed_time":0.3419822386,"remaining_time":0.5151161038},
{"learn":[298055.0642],"iteration":399,"passed_time":0.3427982812,"remaining_time":0.5141974218},
{"learn":[298032.2804],"iteration":400,"passed_time":0.3434649636,"remaining_time":0.5130561426},
{"learn":[297899.3297],"iteration":401,"passed_time":0.3457068319,"remaining_time":0.5142604117},
{"learn":[297729.8888],"iteration":402,"passed_time":0.3463928083,"remaining_time":0.5131426961},
{"learn":[297616.027],"iteration":403,"passed_time":0.3471182489,"remaining_time":0.5120853375},
{"learn":[297491.7873],"iteration":404,"passed_time":0.3478667976,"remaining_time":0.5110635668},
{"learn":[297329.0431],"iteration":405,"passed_time":0.3486980348,"remaining_time":0.5101641198},
{"learn":[297141.674],"iteration":406,"passed_time":0.3493496429,"remaining_time":0.509003288},
{"learn":[297111.8258],"iteration":407,"passed_time":0.3500805589,"remaining_time":0.5079600267},
{"learn":[297076.7342],"iteration":408,"passed_time":0.3506987826,"remaining_time":0.5067554536},
{"learn":[296954.2018],"iteration":409,"passed_time":0.3513469879,"remaining_time":0.505596885},
{"learn":[296882.0722],"iteration":410,"passed_time":0.3524003537,"remaining_time":0.5050214315},
{"learn":[296731.9634],"iteration":411,"passed_time":0.3531184992,"remaining_time":0.5039652368},
{"learn":[296386.2106],"iteration":412,"passed_time":0.3537673006,"remaining_time":0.5028121197},
{"learn":[296144.4876],"iteration":413,"passed_time":0.3544597052,"remaining_time":0.5017231576},
{"learn":[296023.6375],"iteration":414,"passed_time":0.3552253144,"remaining_time":0.5007392987},
{"learn":[295927.0437],"iteration":415,"passed_time":0.3559436881,"remaining_time":0.4996901775},
{"learn":[295737.7329],"iteration":416,"passed_time":0.3566099497,"remaining_time":0.4985697858},
{"learn":[295441.3237],"iteration":417,"passed_time":0.3572583625,"remaining_time":0.4974267152},
{"learn":[295121.4284],"iteration":418,"passed_time":0.3579579304,"remaining_time":0.4963569392},
{"learn":[294960.9419],"iteration":419,"passed_time":0.3586261368,"remaining_time":0.4952456176},
{"learn":[294809.792],"iteration":420,"passed_time":0.3592875476,"remaining_time":0.4941270547},
{"learn":[294687.2644],"iteration":421,"passed_time":0.3601261018,"remaining_time":0.4932532863},
{"learn":[294489.2289],"iteration":422,"passed_time":0.3608897777,"remaining_time":0.4922775454},
{"learn":[294259.4378],"iteration":423,"passed_time":0.3615912301,"remaining_time":0.4912182749},
{"learn":[294067.5289],"iteration":424,"passed_time":0.3622652357,"remaining_time":0.4901235542},
{"learn":[293806.1291],"iteration":425,"passed_time":0.362922717,"remaining_time":0.4890085436},
{"learn":[293689.6125],"iteration":426,"passed_time":0.3635555363,"remaining_time":0.4878625815},
{"learn":[293549.325],"iteration":427,"passed_time":0.36424111,"remaining_time":0.4867895209},
{"learn":[293368.5445],"iteration":428,"passed_time":0.3649013166,"remaining_time":0.485684503},
{"learn":[293142.9011],"iteration":429,"passed_time":0.3655695607,"remaining_time":0.4845922084},
{"learn":[293136.8532],"iteration":430,"passed_time":0.3661799345,"remaining_time":0.483425482},
{"learn":[292875.13],"iteration":431,"passed_time":0.3668701454,"remaining_time":0.4823663023},
{"learn":[292566.6203],"iteration":432,"passed_time":0.3679619268,"remaining_time":0.4818346709},
{"learn":[292423.1277],"iteration":433,"passed_time":0.3686105351,"remaining_time":0.4807224951},
{"learn":[292285.7301],"iteration":434,"passed_time":0.3692952036,"remaining_time":0.4796592874},
{"learn":[292074.2776],"iteration":435,"passed_time":0.3699625275,"remaining_time":0.4785753796},
{"learn":[291760.6209],"iteration":436,"passed_time":0.3706647335,"remaining_time":0.477538318},
{"learn":[291702.7865],"iteration":437,"passed_time":0.3713596126,"remaining_time":0.4764933842},
{"learn":[291618.9328],"iteration":438,"passed_time":0.3720115493,"remaining_time":0.475395169},
{"learn":[291485.7654],"iteration":439,"passed_time":0.3726552737,"remaining_time":0.4742885302},
{"learn":[291368.7151],"iteration":440,"passed_time":0.3733566029,"remaining_time":0.4732570092},
{"learn":[291135.9634],"iteration":441,"passed_time":0.3740379479,"remaining_time":0.4722017533},
{"learn":[291130.1999],"iteration":442,"passed_time":0.3746946376,"remaining_time":0.4711171854},
{"learn":[290942.8027],"iteration":443,"passed_time":0.3754433781,"remaining_time":0.4701498158},
{"learn":[290796.8384],"iteration":444,"passed_time":0.3766152966,"remaining_time":0.4697112127},
{"learn":[290672.6863],"iteration":445,"passed_time":0.3773598514,"remaining_time":0.4687384701},
{"learn":[290608.7903],"iteration":446,"passed_time":0.3780485568,"remaining_time":0.4676976553},
{"learn":[290603.4111],"iteration":447,"passed_time":0.3787177318,"remaining_time":0.4666343481},
{"learn":[290494.1802],"iteration":448,"passed_time":0.379460018,"remaining_time":0.4656625165},
{"learn":[290196.3098],"iteration":449,"passed_time":0.3801268455,"remaining_time":0.4645994778},
{"learn":[290110.1426],"iteration":450,"passed_time":0.3808260847,"remaining_time":0.4635776508},
{"learn":[290005.911],"iteration":451,"passed_time":0.3816089541,"remaining_time":0.4626586435},
{"learn":[289905.9561],"iteration":452,"passed_time":0.3826630446,"remaining_time":0.4620677382},
{"learn":[289679.53],"iteration":453,"passed_time":0.3834496806,"remaining_time":0.4611531401},
{"learn":[289603.2011],"iteration":454,"passed_time":0.3841341569,"remaining_time":0.4601167373},
{"learn":[289543.7872],"iteration":455,"passed_time":0.3848336557,"remaining_time":0.4590997998},
{"learn":[289370.1474],"iteration":456,"passed_time":0.3855276461,"remaining_time":0.4580777064},
{"learn":[289266.3063],"iteration":457,"passed_time":0.3861981149,"remaining_time":0.4570292102},
{"learn":[289217.1787],"iteration":458,"passed_time":0.3868637102,"remaining_time":0.455976617},
{"learn":[289031.569],"iteration":459,"passed_time":0.3875496419,"remaining_time":0.4549495796},
{"learn":[288784.0538],"iteration":460,"passed_time":0.3882313031,"remaining_time":0.453919029},
{"learn":[288623.9255],"iteration":461,"passed_time":0.3889075992,"remaining_time":0.452883741},
{"learn":[288546.4215],"iteration":462,"passed_time":0.389560523,"remaining_time":0.451822896},
{"learn":[288404.5569],"iteration":463,"passed_time":0.3902271484,"remaining_time":0.4507796369},
{"learn":[288277.1027],"iteration":464,"passed_time":0.3909181922,"remaining_time":0.4497660921},
{"learn":[288129.5662],"iteration":465,"passed_time":0.3917110784,"remaining_time":0.4488706349},
{"learn":[287917.301],"iteration":466,"passed_time":0.39252782,"remaining_time":0.4480028438},
{"learn":[287719.9736],"iteration":467,"passed_time":0.3932880484,"remaining_time":0.4470710294},
{"learn":[287449.3967],"iteration":468,"passed_time":0.3939756216,"remaining_time":0.4460576867},
{"learn":[287381.6265],"iteration":469,"passed_time":0.3947142246,"remaining_time":0.4451032746},
{"learn":[287282.5921],"iteration":470,"passed_time":0.3954054127,"remaining_time":0.4440965251},
{"learn":[287277.632],"iteration":471,"passed_time":0.3960715602,"remaining_time":0.4430631013},
{"learn":[287136.2005],"iteration":472,"passed_time":0.3967709388,"remaining_time":0.4420682553},
{"learn":[287098.3],"iteration":473,"passed_time":0.3974380685,"remaining_time":0.4410388692},
{"learn":[287044.2336],"iteration":474,"passed_time":0.3980957915,"remaining_time":0.4400006117},
{"learn":[286947.1865],"iteration":475,"passed_time":0.3987878944,"remaining_time":0.4390017997},
{"learn":[286822.774],"iteration":476,"passed_time":0.3994752461,"remaining_time":0.4379990643},
{"learn":[286623.2052],"iteration":477,"passed_time":0.4002108266,"remaining_time":0.4370503169},
{"learn":[286463.2004],"iteration":478,"passed_time":0.4008636504,"remaining_time":0.4360124465},
{"learn":[286361.2073],"iteration":479,"passed_time":0.4015582744,"remaining_time":0.4350214639},
{"learn":[286127.081],"iteration":480,"passed_time":0.4022352274,"remaining_time":0.4340126466},
{"learn":[286002.3442],"iteration":481,"passed_time":0.4028995201,"remaining_time":0.4329916004},
{"learn":[285975.4991],"iteration":482,"passed_time":0.4035244854,"remaining_time":0.4319299357},
{"learn":[285911.9879],"iteration":483,"passed_time":0.404202633,"remaining_time":0.430926774},
{"learn":[285735.6609],"iteration":484,"passed_time":0.404858018,"remaining_time":0.429900782},
{"learn":[285684.9019],"iteration":485,"passed_time":0.405507432,"remaining_time":0.4288700001},
{"learn":[285626.1669],"iteration":486,"passed_time":0.406158296,"remaining_time":0.4278423118},
{"learn":[285609.1151],"iteration":487,"passed_time":0.4067985282,"remaining_time":0.4268050132},
{"learn":[285569.2136],"iteration":488,"passed_time":0.4078820249,"remaining_time":0.4262325455},
{"learn":[285351.41],"iteration":489,"passed_time":0.4087028853,"remaining_time":0.4253846357},
{"learn":[285335.4012],"iteration":490,"passed_time":0.4093546675,"remaining_time":0.4243615595},
{"learn":[285223.4252],"iteration":491,"passed_time":0.4099779892,"remaining_time":0.4233106067},
{"learn":[285026.3569],"iteration":492,"passed_time":0.4106161773,"remaining_time":0.4222766773},
{"learn":[284859.8121],"iteration":493,"passed_time":0.4112404378,"remaining_time":0.4212300841},
{"learn":[284695.1869],"iteration":494,"passed_time":0.4118996461,"remaining_time":0.4202208511},
{"learn":[284556.4214],"iteration":495,"passed_time":0.4125842724,"remaining_time":0.4192388575},
{"learn":[284476.8112],"iteration":496,"passed_time":0.4132701277,"remaining_time":0.4182593043},
{"learn":[284284.0519],"iteration":497,"passed_time":0.4139247434,"remaining_time":0.4172494402},
{"learn":[284100.9215],"iteration":498,"passed_time":0.414566014,"remaining_time":0.4162276013},
{"learn":[283917.6677],"iteration":499,"passed_time":0.4152730346,"remaining_time":0.4152730346},
{"learn":[283902.2964],"iteration":500,"passed_time":0.4159215168,"remaining_time":0.4142611514},
{"learn":[283804.1426],"iteration":501,"passed_time":0.4165894703,"remaining_time":0.4132700323},
{"learn":[283800.4107],"iteration":502,"passed_time":0.417210552,"remaining_time":0.4122338854},
{"learn":[283703.0807],"iteration":503,"passed_time":0.4179128812,"remaining_time":0.4112793434},
{"learn":[283601.1988],"iteration":504,"passed_time":0.4185822492,"remaining_time":0.4102934918},
{"learn":[283525.2134],"iteration":505,"passed_time":0.4192405746,"remaining_time":0.4092981104},
{"learn":[283489.3111],"iteration":506,"passed_time":0.4198803277,"remaining_time":0.4082859991},
{"learn":[283398.4288],"iteration":507,"passed_time":0.4205335571,"remaining_time":0.4072884057},
{"learn":[283127.4701],"iteration":508,"passed_time":0.4211970917,"remaining_time":0.4063021061},
{"learn":[283030.325],"iteration":509,"passed_time":0.4218276337,"remaining_time":0.4052853736},
{"learn":[282877.7048],"iteration":510,"passed_time":0.4224892701,"remaining_time":0.4042999082},
{"learn":[282783.8423],"iteration":511,"passed_time":0.4231580504,"remaining_time":0.4033225168},
{"learn":[282656.4461],"iteration":512,"passed_time":0.423918237,"remaining_time":0.4024331022},
{"learn":[282549.1102],"iteration":513,"passed_time":0.424803327,"remaining_time":0.4016622897},
{"learn":[282342.6071],"iteration":514,"passed_time":0.4256038166,"remaining_time":0.4008113613},
{"learn":[282235.7718],"iteration":515,"passed_time":0.4263604405,"remaining_time":0.3999194829},
{"learn":[282083.0916],"iteration":516,"passed_time":0.4271693905,"remaining_time":0.3990770128},
{"learn":[281885.2594],"iteration":517,"passed_time":0.4278581992,"remaining_time":0.3981228804},
{"learn":[281743.1384],"iteration":518,"passed_time":0.4285381499,"remaining_time":0.3971615609},
{"learn":[281527.7163],"iteration":519,"passed_time":0.4292200124,"remaining_time":0.3962030884},
{"learn":[281474.0093],"iteration":520,"passed_time":0.4298617187,"remaining_time":0.3952087587},
{"learn":[281342.6726],"iteration":521,"passed_time":0.4305394885,"remaining_time":0.3942488036},
{"learn":[281317.0962],"iteration":522,"passed_time":0.4313025179,"remaining_time":0.3933676884},
{"learn":[281182.5448],"iteration":523,"passed_time":0.4321268498,"remaining_time":0.3925427108},
{"learn":[281178.6048],"iteration":524,"passed_time":0.432753779,"remaining_time":0.3915391334},
{"learn":[281126.7154],"iteration":525,"passed_time":0.4333853354,"remaining_time":0.3905411578},
{"learn":[280974.9438],"iteration":526,"passed_time":0.434046642,"remaining_time":0.3895712745},
{"learn":[280920.2367],"iteration":527,"passed_time":0.4347124886,"remaining_time":0.3886066186},
{"learn":[280834.6591],"iteration":528,"passed_time":0.4353608852,"remaining_time":0.3876275556},
{"learn":[280725.7355],"iteration":529,"passed_time":0.4360080872,"remaining_time":0.3866486811},
{"learn":[280583.1845],"iteration":530,"passed_time":0.4366567563,"remaining_time":0.3856723516},
{"learn":[280414.4966],"iteration":531,"passed_time":0.4373361766,"remaining_time":0.3847243058},
{"learn":[280388.5652],"iteration":532,"passed_time":0.4380269204,"remaining_time":0.3837871891},
{"learn":[280375.8885],"iteration":533,"passed_time":0.4386715645,"remaining_time":0.382810766},
{"learn":[280363.5077],"iteration":534,"passed_time":0.4393260794,"remaining_time":0.3818441625},
{"learn":[280251.449],"iteration":535,"passed_time":0.4401240049,"remaining_time":0.3810028699},
{"learn":[280115.165],"iteration":536,"passed_time":0.440886883,"remaining_time":0.3801315211},
{"learn":[280060.7727],"iteration":537,"passed_time":0.4416860639,"remaining_time":0.37929175},
{"learn":[279979.6396],"iteration":538,"passed_time":0.4423824794,"remaining_time":0.3783642357},
{"learn":[279768.76],"iteration":539,"passed_time":0.4430749519,"remaining_time":0.3774342183},
{"learn":[279606.2303],"iteration":540,"passed_time":0.4439170234,"remaining_time":0.3766320032},
{"learn":[279564.5513],"iteration":541,"passed_time":0.4445428676,"remaining_time":0.375646925},
{"learn":[279416.0227],"iteration":542,"passed_time":0.4452148105,"remaining_time":0.3747019676},
{"learn":[279366.6903],"iteration":543,"passed_time":0.4458922359,"remaining_time":0.3737626095},
{"learn":[279227.6809],"iteration":544,"passed_time":0.4465302355,"remaining_time":0.3727912975},
{"learn":[279032.5026],"iteration":545,"passed_time":0.4472777095,"remaining_time":0.3719122346},
{"learn":[278944.276],"iteration":546,"passed_time":0.4479970231,"remaining_time":0.3710103318},
{"learn":[278756.7535],"iteration":547,"passed_time":0.4486571305,"remaining_time":0.3700602609},
{"learn":[278577.6346],"iteration":548,"passed_time":0.449366935,"remaining_time":0.3691520723},
{"learn":[278434.6989],"iteration":549,"passed_time":0.4500457816,"remaining_time":0.3682192759},
{"learn":[278388.5474],"iteration":550,"passed_time":0.4507079252,"remaining_time":0.3672737903},
{"learn":[278266.0936],"iteration":551,"passed_time":0.4513878941,"remaining_time":0.3663437981},
{"learn":[278156.8096],"iteration":552,"passed_time":0.4520233552,"remaining_time":0.3653787338},
{"learn":[278040.6957],"iteration":553,"passed_time":0.4526960753,"remaining_time":0.3644448548},
{"learn":[277893.7573],"iteration":554,"passed_time":0.4534203932,"remaining_time":0.3635532882},
{"learn":[277645.8828],"iteration":555,"passed_time":0.4540397181,"remaining_time":0.3625784799},
{"learn":[277625.265],"iteration":556,"passed_time":0.4547222205,"remaining_time":0.3616551951},
{"learn":[277480.19],"iteration":557,"passed_time":0.4554879852,"remaining_time":0.3607987266},
{"learn":[277332.6371],"iteration":558,"passed_time":0.456236113,"remaining_time":0.3599286688},
{"learn":[277242.242],"iteration":559,"passed_time":0.4569909305,"remaining_time":0.3590643025},
{"learn":[277209.6718],"iteration":560,"passed_time":0.4577077164,"remaining_time":0.3581705659},
{"learn":[277091.8166],"iteration":561,"passed_time":0.458461626,"remaining_time":0.3573063918},
{"learn":[276940.8334],"iteration":562,"passed_time":0.4591550579,"remaining_time":0.3563956666},
{"learn":[276774.5218],"iteration":563,"passed_time":0.4598099014,"remaining_time":0.3554558813},
{"learn":[276682.6016],"iteration":564,"passed_time":0.4605458317,"remaining_time":0.3545795341},
{"learn":[276645.0047],"iteration":565,"passed_time":0.4611783232,"remaining_time":0.3536243679},
{"learn":[276520.4391],"iteration":566,"passed_time":0.4618312731,"remaining_time":0.3526859634},
{"learn":[276499.1761],"iteration":567,"passed_time":0.4624820371,"remaining_time":0.3517469014},
{"learn":[276472.714],"iteration":568,"passed_time":0.4632652442,"remaining_time":0.3509091744},
{"learn":[276325.2479],"iteration":569,"passed_time":0.4640288961,"remaining_time":0.3500568866},
{"learn":[276208.653],"iteration":570,"passed_time":0.4647120128,"remaining_time":0.3491444019},
{"learn":[276108.2819],"iteration":571,"passed_time":0.4653766077,"remaining_time":0.3482188603},
{"learn":[275901.3256],"iteration":572,"passed_time":0.4660425436,"remaining_time":0.3472952288},
{"learn":[275864.7598],"iteration":573,"passed_time":0.4667861571,"remaining_time":0.3464301444},
{"learn":[275740.975],"iteration":574,"passed_time":0.4674451227,"remaining_time":0.3455029168},
{"learn":[275677.9259],"iteration":575,"passed_time":0.4681600472,"remaining_time":0.3446178125},
{"learn":[275539.2289],"iteration":576,"passed_time":0.4688252531,"remaining_time":0.3436968493},
{"learn":[275429.0602],"iteration":577,"passed_time":0.4694988375,"remaining_time":0.3427828883},
{"learn":[275301.314],"iteration":578,"passed_time":0.4701654426,"remaining_time":0.3418646828},
{"learn":[275138.9808],"iteration":579,"passed_time":0.4708266169,"remaining_time":0.3409434122},
{"learn":[275034.9171],"iteration":580,"passed_time":0.4714933406,"remaining_time":0.3400270391},
{"learn":[275016.6277],"iteration":581,"passed_time":0.4721632572,"remaining_time":0.339113817},
{"learn":[274896.1432],"iteration":582,"passed_time":0.4729104765,"remaining_time":0.3382567216},
{"learn":[274702.0559],"iteration":583,"passed_time":0.4736272773,"remaining_time":0.3373783345},
{"learn":[274591.1664],"iteration":584,"passed_time":0.4743078844,"remaining_time":0.336474824},
{"learn":[274453.8452],"iteration":585,"passed_time":0.4750099768,"remaining_time":0.3355872532},
{"learn":[274379.838],"iteration":586,"passed_time":0.4756725862,"remaining_time":0.3346725351},
{"learn":[274246.7827],"iteration":587,"passed_time":0.4764001656,"remaining_time":0.3338041977},
{"learn":[274128.9007],"iteration":588,"passed_time":0.4770806429,"remaining_time":0.3329034707},
{"learn":[274033.159],"iteration":589,"passed_time":0.4777640787,"remaining_time":0.3320055462},
{"learn":[273735.5135],"iteration":590,"passed_time":0.4784151982,"remaining_time":0.3310859832},
{"learn":[273670.4976],"iteration":591,"passed_time":0.4791246167,"remaining_time":0.3302075061},
{"learn":[273632.1269],"iteration":592,"passed_time":0.4798157816,"remaining_time":0.329317071},
{"learn":[273417.8483],"iteration":593,"passed_time":0.4804757133,"remaining_time":0.3284059589},
{"learn":[273337.482],"iteration":594,"passed_time":0.4811293908,"remaining_time":0.327491434},
{"learn":[273195.1237],"iteration":595,"passed_time":0.4826930954,"remaining_time":0.3271946485},
{"learn":[273080.152],"iteration":596,"passed_time":0.483406562,"remaining_time":0.3263196725},
{"learn":[273043.3206],"iteration":597,"passed_time":0.4841790934,"remaining_time":0.3254849424},
{"learn":[273024.1903],"iteration":598,"passed_time":0.4848053753,"remaining_time":0.3245525134},
{"learn":[272880.6942],"iteration":599,"passed_time":0.4854688864,"remaining_time":0.3236459242},
{"learn":[272737.3514],"iteration":600,"passed_time":0.4861560731,"remaining_time":0.3227558621},
{"learn":[272588.4945],"iteration":601,"passed_time":0.4868302246,"remaining_time":0.3218578561},
{"learn":[272441.0353],"iteration":602,"passed_time":0.4874938216,"remaining_time":0.3209536438},
{"learn":[272299.5374],"iteration":603,"passed_time":0.4882223038,"remaining_time":0.3200927687},
{"learn":[272258.0386],"iteration":604,"passed_time":0.4889023669,"remaining_time":0.3192007189},
{"learn":[272103.535],"iteration":605,"passed_time":0.4895843216,"remaining_time":0.3183105985},
{"learn":[272096.9685],"iteration":606,"passed_time":0.4902112926,"remaining_time":0.317385565},
{"learn":[271969.0475],"iteration":607,"passed_time":0.4909110787,"remaining_time":0.3165084587},
{"learn":[271761.6927],"iteration":608,"passed_time":0.4915826343,"remaining_time":0.3156138096},
{"learn":[271685.9064],"iteration":609,"passed_time":0.4922652488,"remaining_time":0.3147269623},
{"learn":[271607.7966],"iteration":610,"passed_time":0.4929785099,"remaining_time":0.3138602952},
{"learn":[271514.9821],"iteration":611,"passed_time":0.4936806299,"remaining_time":0.312987066},
{"learn":[271419.8363],"iteration":612,"passed_time":0.4943407861,"remaining_time":0.3120879025},
{"learn":[271273.1077],"iteration":613,"passed_time":0.4950091505,"remaining_time":0.3111946777},
{"learn":[271180.9032],"iteration":614,"passed_time":0.4956896162,"remaining_time":0.3103097597},
{"learn":[271111.6843],"iteration":615,"passed_time":0.4965151737,"remaining_time":0.3095159524},
{"learn":[271012.3782],"iteration":616,"passed_time":0.4971993379,"remaining_time":0.3086342729},
{"learn":[270822.9628],"iteration":617,"passed_time":0.4978707819,"remaining_time":0.30774537},
{"learn":[270747.4453],"iteration":618,"passed_time":0.4986911975,"remaining_time":0.3069488631},
{"learn":[270707.721],"iteration":619,"passed_time":0.4993787347,"remaining_time":0.3060708374},
{"learn":[270676.9856],"iteration":620,"passed_time":0.5000444453,"remaining_time":0.3051801043},
{"learn":[270578.0667],"iteration":621,"passed_time":0.5006982885,"remaining_time":0.3042828827},
{"learn":[270412.4667],"iteration":622,"passed_time":0.5013530299,"remaining_time":0.303386986},
{"learn":[270372.3518],"iteration":623,"passed_time":0.5019957266,"remaining_time":0.3024846045},
{"learn":[270349.9184],"iteration":624,"passed_time":0.5026206184,"remaining_time":0.301572371},
{"learn":[270308.9786],"iteration":625,"passed_time":0.5032920235,"remaining_time":0.3006888447},
{"learn":[270151.4241],"iteration":626,"passed_time":0.5040194259,"remaining_time":0.2998393076},
{"learn":[270031.4963],"iteration":627,"passed_time":0.504865849,"remaining_time":0.2990606622},
{"learn":[270012.2144],"iteration":628,"passed_time":0.5055422493,"remaining_time":0.2981815175},
{"learn":[269851.2244],"iteration":629,"passed_time":0.5062187893,"remaining_time":0.2973030985},
{"learn":[269715.3561],"iteration":630,"passed_time":0.5069344732,"remaining_time":0.2964482101},
{"learn":[269689.3241],"iteration":631,"passed_time":0.5076249656,"remaining_time":0.2955790939},
{"learn":[269625.3307],"iteration":632,"passed_time":0.5083106654,"remaining_time":0.2947077633},
{"learn":[269504.6324],"iteration":633,"passed_time":0.5089901556,"remaining_time":0.2938334337},
{"learn":[269495.2606],"iteration":634,"passed_time":0.5096259428,"remaining_time":0.2929345971},
{"learn":[269404.5994],"iteration":635,"passed_time":0.5103750612,"remaining_time":0.2921014501},
{"learn":[269276.8258],"iteration":636,"passed_time":0.5110352111,"remaining_time":0.2912178676},
{"learn":[269158.8068],"iteration":637,"passed_time":0.5117197167,"remaining_time":0.2903488048},
{"learn":[269124.8716],"iteration":638,"passed_time":0.512361855,"remaining_time":0.2894563844},
{"learn":[269115.7238],"iteration":639,"passed_time":0.5130044889,"remaining_time":0.288565025},
{"learn":[269109.7021],"iteration":640,"passed_time":0.5136256731,"remaining_time":0.2876624285},
{"learn":[269012.7689],"iteration":641,"passed_time":0.5142936357,"remaining_time":0.2867867937},
{"learn":[268912.2138],"iteration":642,"passed_time":0.514974874,"remaining_time":0.2859191758},
{"learn":[268798.6759],"iteration":643,"passed_time":0.5156111197,"remaining_time":0.2850272649},
{"learn":[268789.8373],"iteration":644,"passed_time":0.5162709138,"remaining_time":0.2841491076},
{"learn":[268679.6096],"iteration":645,"passed_time":0.5169145881,"remaining_time":0.2832627929},
{"learn":[268574.5134],"iteration":646,"passed_time":0.5175510306,"remaining_time":0.2823732825},
{"learn":[268523.7374],"iteration":647,"passed_time":0.5182585649,"remaining_time":0.2815231711},
{"learn":[268515.1276],"iteration":648,"passed_time":0.518920279,"remaining_time":0.2806487179},
{"learn":[268388.9026],"iteration":649,"passed_time":0.5195942206,"remaining_time":0.2797815034},
{"learn":[268251.6657],"iteration":650,"passed_time":0.5203306692,"remaining_time":0.2789483925},
{"learn":[268243.2843],"iteration":651,"passed_time":0.5210175359,"remaining_time":0.2780891143},
{"learn":[268046.901],"iteration":652,"passed_time":0.5217247846,"remaining_time":0.2772411949},
{"learn":[268010.8737],"iteration":653,"passed_time":0.5224089153,"remaining_time":0.2763814751},
{"learn":[267973.4824],"iteration":654,"passed_time":0.5230848716,"remaining_time":0.2755179858},
{"learn":[267891.3746],"iteration":655,"passed_time":0.5237996605,"remaining_time":0.2746754317},
{"learn":[267796.4106],"iteration":656,"passed_time":0.5244829049,"remaining_time":0.2738167982},
{"learn":[267677.8625],"iteration":657,"passed_time":0.5251506406,"remaining_time":0.2729506369},
{"learn":[267643.7981],"iteration":658,"passed_time":0.5258694512,"remaining_time":0.2721115066},
{"learn":[267617.7649],"iteration":659,"passed_time":0.5266093754,"remaining_time":0.2712836176},
{"learn":[267603.1259],"iteration":660,"passed_time":0.5272945105,"remaining_time":0.2704278957},
{"learn":[267532.2476],"iteration":661,"passed_time":0.5279922278,"remaining_time":0.2695791133},
{"learn":[267467.8677],"iteration":662,"passed_time":0.5287125389,"remaining_time":0.2687422709},
{"learn":[267287.5496],"iteration":663,"passed_time":0.5293842334,"remaining_time":0.2678811783},
{"learn":[267274.742],"iteration":664,"passed_time":0.5307685987,"remaining_time":0.26737967},
{"learn":[267269.7605],"iteration":665,"passed_time":0.5314094944,"remaining_time":0.2665026593},
{"learn":[267194.6387],"iteration":666,"passed_time":0.5320759784,"remaining_time":0.2656391316},
{"learn":[267051.3472],"iteration":667,"passed_time":0.5327599429,"remaining_time":0.2647848818},
{"learn":[266964.931],"iteration":668,"passed_time":0.5334141407,"remaining_time":0.2639164134},
{"learn":[266808.4213],"iteration":669,"passed_time":0.5340890677,"remaining_time":0.2630587946},
{"learn":[266678.0749],"iteration":670,"passed_time":0.5347731835,"remaining_time":0.2622062256},
{"learn":[266569.934],"iteration":671,"passed_time":0.5354633919,"remaining_time":0.2613571318},
{"learn":[266501.8234],"iteration":672,"passed_time":0.5361610621,"remaining_time":0.2605121357},
{"learn":[266377.3309],"iteration":673,"passed_time":0.5369434788,"remaining_time":0.2597085669},
{"learn":[266232.7777],"iteration":674,"passed_time":0.5376613577,"remaining_time":0.258873987},
{"learn":[266139.9107],"iteration":675,"passed_time":0.5383818201,"remaining_time":0.2580409907},
{"learn":[266067.7244],"iteration":676,"passed_time":0.5390547047,"remaining_time":0.2571856272},
{"learn":[266061.3014],"iteration":677,"passed_time":0.5396753193,"remaining_time":0.2563059776},
{"learn":[265996.2198],"iteration":678,"passed_time":0.5403128638,"remaining_time":0.2554350947},
{"learn":[265886.5194],"iteration":679,"passed_time":0.5409700024,"remaining_time":0.2545741188},
{"learn":[265884.3412],"iteration":680,"passed_time":0.5416326532,"remaining_time":0.2537163236},
{"learn":[265861.9607],"iteration":681,"passed_time":0.5422822395,"remaining_time":0.252853009},
{"learn":[265775.9368],"iteration":682,"passed_time":0.5435304699,"remaining_time":0.2522681683},
{"learn":[265654.0124],"iteration":683,"passed_time":0.5442688547,"remaining_time":0.2514458452},
{"learn":[265535.3815],"iteration":684,"passed_time":0.5450767817,"remaining_time":0.2506557463},
{"learn":[265421.4691],"iteration":685,"passed_time":0.5468168465,"remaining_time":0.2502922592},
{"learn":[265364.5788],"iteration":686,"passed_time":0.5475399288,"remaining_time":0.2494614232},
{"learn":[265346.6228],"iteration":687,"passed_time":0.5482068799,"remaining_time":0.2486054455},
{"learn":[265288.8729],"iteration":688,"passed_time":0.5489227957,"remaining_time":0.2477721182},
{"learn":[265229.9597],"iteration":689,"passed_time":0.5495867581,"remaining_time":0.2469157899},
{"learn":[265105.2174],"iteration":690,"passed_time":0.5502932214,"remaining_time":0.2460790237},
{"learn":[265065.7111],"iteration":691,"passed_time":0.5518272681,"remaining_time":0.2456109806},
{"learn":[264972.7431],"iteration":692,"passed_time":0.5525436956,"remaining_time":0.2447776545},
{"learn":[264917.3748],"iteration":693,"passed_time":0.5532224132,"remaining_time":0.2439280381},
{"learn":[264829.2889],"iteration":694,"passed_time":0.5539256142,"remaining_time":0.243089658},
{"learn":[264815.1636],"iteration":695,"passed_time":0.5545992197,"remaining_time":0.2422387396},
{"learn":[264743.1149],"iteration":696,"passed_time":0.5552547565,"remaining_time":0.2413804752},
{"learn":[264602.3252],"iteration":697,"passed_time":0.5559532194,"remaining_time":0.2405413643},
{"learn":[264486.9044],"iteration":698,"passed_time":0.5566734714,"remaining_time":0.2397120385},
{"learn":[264396.7551],"iteration":699,"passed_time":0.5573782101,"remaining_time":0.2388763758},
{"learn":[264336.0308],"iteration":700,"passed_time":0.5580872008,"remaining_time":0.2380429002},
{"learn":[264201.2044],"iteration":701,"passed_time":0.5587993057,"remaining_time":0.2372111013},
{"learn":[264082.2746],"iteration":702,"passed_time":0.5594954149,"remaining_time":0.2363728851},
{"learn":[263998.1894],"iteration":703,"passed_time":0.5601982075,"remaining_time":0.2355378827},
{"learn":[263906.7148],"iteration":704,"passed_time":0.5608992305,"remaining_time":0.2347025149},
{"learn":[263828.97],"iteration":705,"passed_time":0.5615982411,"remaining_time":0.2338666897},
{"learn":[263758.5948],"iteration":706,"passed_time":0.5624242554,"remaining_time":0.2330838852},
{"learn":[263631.5961],"iteration":707,"passed_time":0.5631214233,"remaining_time":0.2322478187},
{"learn":[263629.6126],"iteration":708,"passed_time":0.5637755993,"remaining_time":0.2313944984},
{"learn":[263525.3436],"iteration":709,"passed_time":0.5644458486,"remaining_time":0.2305483044},
{"learn":[263461.3293],"iteration":710,"passed_time":0.5652323689,"remaining_time":0.2297498658},
{"learn":[263391.4594],"iteration":711,"passed_time":0.566061688,"remaining_time":0.2289687727},
{"learn":[263268.9098],"iteration":712,"passed_time":0.5667571289,"remaining_time":0.228133655},
{"learn":[263209.9043],"iteration":713,"passed_time":0.5675745385,"remaining_time":0.2273477843},
{"learn":[263206.4587],"iteration":714,"passed_time":0.5683870765,"remaining_time":0.2265598837},
{"learn":[263194.8426],"iteration":715,"passed_time":0.5691594836,"remaining_time":0.2257559963},
{"learn":[263171.4378],"iteration":716,"passed_time":0.5698622964,"remaining_time":0.2249247279},
{"learn":[263095.8054],"iteration":717,"passed_time":0.5705282827,"remaining_time":0.2240793534},
{"learn":[263061.4082],"iteration":718,"passed_time":0.5712002682,"remaining_time":0.2232368225},
{"learn":[262948.3438],"iteration":719,"passed_time":0.5718771203,"remaining_time":0.2223966579},
{"learn":[262849.7725],"iteration":720,"passed_time":0.5725301149,"remaining_time":0.2215477143},
{"learn":[262771.8621],"iteration":721,"passed_time":0.5732030466,"remaining_time":0.2207069902},
{"learn":[262727.6582],"iteration":722,"passed_time":0.5738843027,"remaining_time":0.2198699196},
{"learn":[262662.3309],"iteration":723,"passed_time":0.5752311147,"remaining_time":0.2192869995},
{"learn":[262632.9953],"iteration":724,"passed_time":0.5762717108,"remaining_time":0.2185858213},
{"learn":[262630.3875],"iteration":725,"passed_time":0.576915839,"remaining_time":0.217734077},
{"learn":[262549.8951],"iteration":726,"passed_time":0.5776010122,"remaining_time":0.2168983168},
{"learn":[262532.9319],"iteration":727,"passed_time":0.5782762456,"remaining_time":0.2160592566},
{"learn":[262451.0945],"iteration":728,"passed_time":0.578935742,"remaining_time":0.2152147957},
{"learn":[262423.0481],"iteration":729,"passed_time":0.5799669571,"remaining_time":0.2145083266},
{"learn":[262399.7501],"iteration":730,"passed_time":0.580605387,"remaining_time":0.2136564283},
{"learn":[262331.5647],"iteration":731,"passed_time":0.5813455803,"remaining_time":0.2128423709},
{"learn":[262158.0154],"iteration":732,"passed_time":0.5820241136,"remaining_time":0.212006055},
{"learn":[262065.6907],"iteration":733,"passed_time":0.5827069475,"remaining_time":0.2111717276},
{"learn":[262035.3351],"iteration":734,"passed_time":0.5834750411,"remaining_time":0.2103685522},
{"learn":[262033.7207],"iteration":735,"passed_time":0.5840032344,"remaining_time":0.209479421},
{"learn":[261933.8245],"iteration":736,"passed_time":0.5847386252,"remaining_time":0.2086652082},
{"learn":[261867.5994],"iteration":737,"passed_time":0.5855012483,"remaining_time":0.2078608768},
{"learn":[261756.5779],"iteration":738,"passed_time":0.5862620967,"remaining_time":0.2070560315},
{"learn":[261693.5869],"iteration":739,"passed_time":0.5869864977,"remaining_time":0.2062384992},
{"learn":[261632.2003],"iteration":740,"passed_time":0.5877334119,"remaining_time":0.2054290873},
{"learn":[261493.8731],"iteration":741,"passed_time":0.5884045004,"remaining_time":0.2045934786},
{"learn":[261391.7365],"iteration":742,"passed_time":0.5890838352,"remaining_time":0.2037611651},
{"learn":[261296.9729],"iteration":743,"passed_time":0.5898144896,"remaining_time":0.2029469212},
{"learn":[261267.3277],"iteration":744,"passed_time":0.5908492254,"remaining_time":0.2022369832},
{"learn":[261265.0869],"iteration":745,"passed_time":0.5914986199,"remaining_time":0.2013949725},
{"learn":[261194.1293],"iteration":746,"passed_time":0.5921763219,"remaining_time":0.2005630648},
{"learn":[261069.48],"iteration":747,"passed_time":0.5928222656,"remaining_time":0.1997208702},
{"learn":[261006.9344],"iteration":748,"passed_time":0.5935630322,"remaining_time":0.1989109761},
{"learn":[260914.6638],"iteration":749,"passed_time":0.594231011,"remaining_time":0.1980770037},
{"learn":[260896.5454],"iteration":750,"passed_time":0.5948781989,"remaining_time":0.1972365799},
{"learn":[260826.2811],"iteration":751,"passed_time":0.595595886,"remaining_time":0.1964199198},
{"learn":[260810.4395],"iteration":752,"passed_time":0.5962403218,"remaining_time":0.1955794947},
{"learn":[260790.261],"iteration":753,"passed_time":0.5968702653,"remaining_time":0.1947348611},
{"learn":[260707.4751],"iteration":754,"passed_time":0.5981365169,"remaining_time":0.1940972803},
{"learn":[260605.1148],"iteration":755,"passed_time":0.598845102,"remaining_time":0.1932780488},
{"learn":[260507.2029],"iteration":756,"passed_time":0.5996041973,"remaining_time":0.1924753236},
{"learn":[260404.1549],"iteration":757,"passed_time":0.6005369308,"remaining_time":0.1917281494},
{"learn":[260279.0636],"iteration":758,"passed_time":0.6012101676,"remaining_time":0.1908980901},
{"learn":[260236.541],"iteration":759,"passed_time":0.601882874,"remaining_time":0.190068276},
{"learn":[260217.7532],"iteration":760,"passed_time":0.6026087689,"remaining_time":0.1892555792},
{"learn":[260123.1339],"iteration":761,"passed_time":0.6033024219,"remaining_time":0.1884330399},
{"learn":[260043.6704],"iteration":762,"passed_time":0.6039773469,"remaining_time":0.1876050212},
{"learn":[259959.5332],"iteration":763,"passed_time":0.6047468984,"remaining_time":0.1868066335},
{"learn":[259865.5403],"iteration":764,"passed_time":0.6053989261,"remaining_time":0.1859722191},
{"learn":[259860.7211],"iteration":765,"passed_time":0.6060340412,"remaining_time":0.1851331144},
{"learn":[259775.1588],"iteration":766,"passed_time":0.6067305849,"remaining_time":0.1843132025},
{"learn":[259655.1151],"iteration":767,"passed_time":0.6075600024,"remaining_time":0.1835337507},
{"learn":[259557.9169],"iteration":768,"passed_time":0.6082674206,"remaining_time":0.1827175217},
{"learn":[259405.227],"iteration":769,"passed_time":0.6089334739,"remaining_time":0.1818892195},
{"learn":[259359.0217],"iteration":770,"passed_time":0.6096254391,"remaining_time":0.1810690344},
{"learn":[259355.0063],"iteration":771,"passed_time":0.6102714382,"remaining_time":0.1802356061},
{"learn":[259226.7933],"iteration":772,"passed_time":0.610946445,"remaining_time":0.1794111811},
{"learn":[259108.5696],"iteration":773,"passed_time":0.6116363033,"remaining_time":0.1785914787},
{"learn":[259004.8382],"iteration":774,"passed_time":0.612285344,"remaining_time":0.1777602612},
{"learn":[258871.231],"iteration":775,"passed_time":0.6129426227,"remaining_time":0.1769318911},
{"learn":[258761.6719],"iteration":776,"passed_time":0.6135982661,"remaining_time":0.1761034921},
{"learn":[258592.4875],"iteration":777,"passed_time":0.6143261927,"remaining_time":0.175296163},
{"learn":[258528.0059],"iteration":778,"passed_time":0.6151016058,"remaining_time":0.1745025095},
{"learn":[258517.7912],"iteration":779,"passed_time":0.6158117464,"remaining_time":0.1736904926},
{"learn":[258392.2841],"iteration":780,"passed_time":0.6165203517,"remaining_time":0.1728783061},
{"learn":[258261.422],"iteration":781,"passed_time":0.6171865327,"remaining_time":0.1720545577},
{"learn":[258215.9724],"iteration":782,"passed_time":0.6178706547,"remaining_time":0.171236184},
{"learn":[258156.0966],"iteration":783,"passed_time":0.6185471728,"remaining_time":0.1704160578},
{"learn":[258087.1526],"iteration":784,"passed_time":0.6192645358,"remaining_time":0.1696074843},
{"learn":[257969.2803],"iteration":785,"passed_time":0.6199149307,"remaining_time":0.1687809099},
{"learn":[257881.0536],"iteration":786,"passed_time":0.6205863122,"remaining_time":0.1679604632},
{"learn":[257746.1406],"iteration":787,"passed_time":0.6212822921,"remaining_time":0.1671470126},
{"learn":[257742.1374],"iteration":788,"passed_time":0.6219137254,"remaining_time":0.1663165983},
{"learn":[257721.4219],"iteration":789,"passed_time":0.62259088,"remaining_time":0.1654988415},
{"learn":[257672.5618],"iteration":790,"passed_time":0.623277829,"remaining_time":0.1646840282},
{"learn":[257647.5519],"iteration":791,"passed_time":0.6239120616,"remaining_time":0.163855693},
{"learn":[257503.6887],"iteration":792,"passed_time":0.6245830034,"remaining_time":0.1630374296},
{"learn":[257394.7472],"iteration":793,"passed_time":0.6254219557,"remaining_time":0.162263127},
{"learn":[257381.3859],"iteration":794,"passed_time":0.6260762118,"remaining_time":0.1614410358},
{"learn":[257286.5327],"iteration":795,"passed_time":0.626782747,"remaining_time":0.1606327643},
{"learn":[257281.024],"iteration":796,"passed_time":0.6273905042,"remaining_time":0.1597995889},
{"learn":[257199.4613],"iteration":797,"passed_time":0.6280485307,"remaining_time":0.1589797033},
{"learn":[257176.7071],"iteration":798,"passed_time":0.6286942206,"remaining_time":0.1581571193},
{"learn":[257097.5949],"iteration":799,"passed_time":0.6294024428,"remaining_time":0.1573506107},
{"learn":[257015.1697],"iteration":800,"passed_time":0.6301106154,"remaining_time":0.1565443352},
{"learn":[256997.461],"iteration":801,"passed_time":0.631118784,"remaining_time":0.1558123681},
{"learn":[256978.4788],"iteration":802,"passed_time":0.6319903456,"remaining_time":0.1550461994},
{"learn":[256826.4442],"iteration":803,"passed_time":0.6328007077,"remaining_time":0.1542648491},
{"learn":[256732.8578],"iteration":804,"passed_time":0.6335655005,"remaining_time":0.1534723883},
{"learn":[256652.3817],"iteration":805,"passed_time":0.6342385409,"remaining_time":0.1526579118},
{"learn":[256489.7577],"iteration":806,"passed_time":0.6351157785,"remaining_time":0.1518926211},
{"learn":[256410.6331],"iteration":807,"passed_time":0.6363339513,"remaining_time":0.1512080676},
{"learn":[256347.6318],"iteration":808,"passed_time":0.6370187946,"remaining_time":0.1503962791},
{"learn":[256338.5163],"iteration":809,"passed_time":0.6377090353,"remaining_time":0.14958607},
{"learn":[256212.6089],"iteration":810,"passed_time":0.6383797551,"remaining_time":0.1487716075},
{"learn":[256127.7875],"iteration":811,"passed_time":0.6391314375,"remaining_time":0.1479762442},
{"learn":[256010.1063],"iteration":812,"passed_time":0.6398319144,"remaining_time":0.1471692103},
{"learn":[255918.5336],"iteration":813,"passed_time":0.6404993446,"remaining_time":0.1463548871},
{"learn":[255806.6902],"iteration":814,"passed_time":0.6412527946,"remaining_time":0.1455604503},
{"learn":[255707.0863],"iteration":815,"passed_time":0.6419773956,"remaining_time":0.1447596088},
{"learn":[255598.3361],"iteration":816,"passed_time":0.6426525248,"remaining_time":0.1439478728},
{"learn":[255513.247],"iteration":817,"passed_time":0.643410991,"remaining_time":0.1431550127},
{"learn":[255439.094],"iteration":818,"passed_time":0.6441124741,"remaining_time":0.1423496432},
{"learn":[255328.4642],"iteration":819,"passed_time":0.6448107398,"remaining_time":0.1415438209},
{"learn":[255225.8572],"iteration":820,"passed_time":0.6454779567,"remaining_time":0.1407314912},
{"learn":[255095.9344],"iteration":821,"passed_time":0.6461358538,"remaining_time":0.1399174963},
{"learn":[255068.8585],"iteration":822,"passed_time":0.6469697531,"remaining_time":0.139141733},
{"learn":[254997.0237],"iteration":823,"passed_time":0.6479885585,"remaining_time":0.1384053232},
{"learn":[254969.5522],"iteration":824,"passed_time":0.6487359092,"remaining_time":0.1376106474},
{"learn":[254967.5103],"iteration":825,"passed_time":0.649465398,"remaining_time":0.1368123235},
{"learn":[254818.4395],"iteration":826,"passed_time":0.6501271406,"remaining_time":0.1359999943},
{"learn":[254729.3922],"iteration":827,"passed_time":0.650778029,"remaining_time":0.1351857741},
{"learn":[254694.0964],"iteration":828,"passed_time":0.6514463277,"remaining_time":0.1343755393},
{"learn":[254619.8493],"iteration":829,"passed_time":0.6522252395,"remaining_time":0.1335883021},
{"learn":[254596.9855],"iteration":830,"passed_time":0.6528626931,"remaining_time":0.1327723166},
{"learn":[254526.0921],"iteration":831,"passed_time":0.6536069403,"remaining_time":0.1319783245},
{"learn":[254373.1976],"iteration":832,"passed_time":0.6546329494,"remaining_time":0.1312409394},
{"learn":[254353.5234],"iteration":833,"passed_time":0.6553913057,"remaining_time":0.1304495884},
{"learn":[254341.7913],"iteration":834,"passed_time":0.6560054796,"remaining_time":0.1296298253},
{"learn":[254245.9466],"iteration":835,"passed_time":0.6566441927,"remaining_time":0.128815368},
{"learn":[254161.0042],"iteration":836,"passed_time":0.6573999311,"remaining_time":0.1280241204},
{"learn":[254127.703],"iteration":837,"passed_time":0.6580377571,"remaining_time":0.1272101631},
{"learn":[253978.2642],"iteration":838,"passed_time":0.6586831379,"remaining_time":0.1263980753},
{"learn":[253966.8797],"iteration":839,"passed_time":0.6593376259,"remaining_time":0.1255881192},
{"learn":[253888.7603],"iteration":840,"passed_time":0.6599896904,"remaining_time":0.1247780746},
{"learn":[253820.2097],"iteration":841,"passed_time":0.660615895,"remaining_time":0.1239635527},
{"learn":[253733.5282],"iteration":842,"passed_time":0.6612646004,"remaining_time":0.1231536682},
{"learn":[253682.7797],"iteration":843,"passed_time":0.6619406348,"remaining_time":0.1223492169},
{"learn":[253564.6893],"iteration":844,"passed_time":0.6626379284,"remaining_time":0.1215489691},
{"learn":[253549.9922],"iteration":845,"passed_time":0.6634639336,"remaining_time":0.1207723945},
{"learn":[253526.248],"iteration":846,"passed_time":0.6644051899,"remaining_time":0.1200165219},
{"learn":[253451.1515],"iteration":847,"passed_time":0.6651018452,"remaining_time":0.1192163685},
{"learn":[253272.943],"iteration":848,"passed_time":0.6657748331,"remaining_time":0.1184122495},
{"learn":[253206.7509],"iteration":849,"passed_time":0.6664369656,"remaining_time":0.1176065233},
{"learn":[253068.3348],"iteration":850,"passed_time":0.6670930724,"remaining_time":0.1168000797},
{"learn":[252954.8532],"iteration":851,"passed_time":0.6677620977,"remaining_time":0.1159962329},
{"learn":[252949.9367],"iteration":852,"passed_time":0.6683869378,"remaining_time":0.1151850878},
{"learn":[252844.4407],"iteration":853,"passed_time":0.6690445364,"remaining_time":0.1143799793},
{"learn":[252779.6672],"iteration":854,"passed_time":0.669782309,"remaining_time":0.1135888126},
{"learn":[252676.7601],"iteration":855,"passed_time":0.670513352,"remaining_time":0.1127966387},
{"learn":[252602.9542],"iteration":856,"passed_time":0.6712153679,"remaining_time":0.1119997638},
{"learn":[252583.2001],"iteration":857,"passed_time":0.6719519293,"remaining_time":0.1112088275},
{"learn":[252534.5715],"iteration":858,"passed_time":0.6726998902,"remaining_time":0.1104198888},
{"learn":[252493.1177],"iteration":859,"passed_time":0.6734379191,"remaining_time":0.1096294287},
{"learn":[252390.7423],"iteration":860,"passed_time":0.6741006088,"remaining_time":0.1088269276},
{"learn":[252275.1085],"iteration":861,"passed_time":0.6748465074,"remaining_time":0.1080380719},
{"learn":[252252.0557],"iteration":862,"passed_time":0.6755088482,"remaining_time":0.1072360512},
{"learn":[252166.1624],"iteration":863,"passed_time":0.676715989,"remaining_time":0.1065201094},
{"learn":[252057.0821],"iteration":864,"passed_time":0.677386109,"remaining_time":0.1057192193},
{"learn":[251961.6415],"iteration":865,"passed_time":0.6781479826,"remaining_time":0.1049328287},
{"learn":[251867.7173],"iteration":866,"passed_time":0.6788066382,"remaining_time":0.1041306608},
{"learn":[251841.9707],"iteration":867,"passed_time":0.679452949,"remaining_time":0.1033269462},
{"learn":[251764.0181],"iteration":868,"passed_time":0.6801003441,"remaining_time":0.1025237573},
{"learn":[251748.1837],"iteration":869,"passed_time":0.6808880507,"remaining_time":0.1017418926},
{"learn":[251725.3546],"iteration":870,"passed_time":0.6816328936,"remaining_time":0.1009536662},
{"learn":[251624.6616],"iteration":871,"passed_time":0.6823947039,"remaining_time":0.1001680299},
{"learn":[251558.5267],"iteration":872,"passed_time":0.6831561133,"remaining_time":0.09938238991},
{"learn":[251471.6227],"iteration":873,"passed_time":0.683869219,"remaining_time":0.09858984164},
{"learn":[251468.3339],"iteration":874,"passed_time":0.6845809428,"remaining_time":0.09779727755},
{"learn":[251449.694],"iteration":875,"passed_time":0.685301893,"remaining_time":0.09700620403},
{"learn":[251396.0261],"iteration":876,"passed_time":0.6860940669,"remaining_time":0.09622527963},
{"learn":[251294.2919],"iteration":877,"passed_time":0.6867952846,"remaining_time":0.09543169102},
{"learn":[251250.3472],"iteration":878,"passed_time":0.6874980478,"remaining_time":0.09463852535},
{"learn":[251143.1218],"iteration":879,"passed_time":0.6881467049,"remaining_time":0.09383818703},
{"learn":[251068.6751],"iteration":880,"passed_time":0.6887441767,"remaining_time":0.09303127925},
{"learn":[250881.7433],"iteration":881,"passed_time":0.689354097,"remaining_time":0.09222651185},
{"learn":[250801.4088],"iteration":882,"passed_time":0.6900038805,"remaining_time":0.09142746775},
{"learn":[250707.9981],"iteration":883,"passed_time":0.6906940195,"remaining_time":0.09063405686},
{"learn":[250634.6161],"iteration":884,"passed_time":0.6914386168,"remaining_time":0.08984795586},
{"learn":[250614.1807],"iteration":885,"passed_time":0.6920712034,"remaining_time":0.08904753633},
{"learn":[250536.1329],"iteration":886,"passed_time":0.6927207926,"remaining_time":0.08824966129},
{"learn":[250418.4636],"iteration":887,"passed_time":0.6933633004,"remaining_time":0.08745122708},
{"learn":[250310.0332],"iteration":888,"passed_time":0.6940595771,"remaining_time":0.08665985721},
{"learn":[250307.4182],"iteration":889,"passed_time":0.6947226805,"remaining_time":0.08586460097},
{"learn":[250303.2993],"iteration":890,"passed_time":0.6955067115,"remaining_time":0.08508443497},
{"learn":[250199.9908],"iteration":891,"passed_time":0.6963645369,"remaining_time":0.08431319505},
{"learn":[250130.2893],"iteration":892,"passed_time":0.6971649088,"remaining_time":0.08353487708},
{"learn":[249964.5064],"iteration":893,"passed_time":0.6978765929,"remaining_time":0.08274599423},
{"learn":[249854.0971],"iteration":894,"passed_time":0.6985616751,"remaining_time":0.081954163},
{"learn":[249838.6421],"iteration":895,"passed_time":0.6993360134,"remaining_time":0.08117293013},
{"learn":[249831.6978],"iteration":896,"passed_time":0.6999818724,"remaining_time":0.08037695971},
{"learn":[249760.5117],"iteration":897,"passed_time":0.7006474507,"remaining_time":0.07958356344},
{"learn":[249700.5749],"iteration":898,"passed_time":0.7013094488,"remaining_time":0.07879004931},
{"learn":[249654.5788],"iteration":899,"passed_time":0.7019855606,"remaining_time":0.07799839562},
{"learn":[249651.9231],"iteration":900,"passed_time":0.7026278051,"remaining_time":0.07720327714},
{"learn":[249590.0252],"iteration":901,"passed_time":0.703362136,"remaining_time":0.07641850258},
{"learn":[249567.8121],"iteration":902,"passed_time":0.7039919249,"remaining_time":0.07562260987},
{"learn":[249504.2474],"iteration":903,"passed_time":0.7046710889,"remaining_time":0.07483232803},
{"learn":[249331.8123],"iteration":904,"passed_time":0.7053212515,"remaining_time":0.07403924739},
{"learn":[249185.0321],"iteration":905,"passed_time":0.7060008549,"remaining_time":0.07324953683},
{"learn":[249035.9036],"iteration":906,"passed_time":0.7066761391,"remaining_time":0.07245962617},
{"learn":[249031.7925],"iteration":907,"passed_time":0.7072752478,"remaining_time":0.07166224978},
{"learn":[248959.9002],"iteration":908,"passed_time":0.707966581,"remaining_time":0.07087454222},
{"learn":[248955.8174],"iteration":909,"passed_time":0.7085735504,"remaining_time":0.07007870278},
{"learn":[248902.7353],"iteration":910,"passed_time":0.7092393548,"remaining_time":0.06928902588},
{"learn":[248824.375],"iteration":911,"passed_time":0.7099119049,"remaining_time":0.06850027153},
{"learn":[248743.2129],"iteration":912,"passed_time":0.7106139754,"remaining_time":0.06771458473},
{"learn":[248700.868],"iteration":913,"passed_time":0.7112686288,"remaining_time":0.06692461934},
{"learn":[248661.1921],"iteration":914,"passed_time":0.7120822346,"remaining_time":0.06614971578},
{"learn":[248521.185],"iteration":915,"passed_time":0.712884426,"remaining_time":0.06537368099},
{"learn":[248390.0538],"iteration":916,"passed_time":0.7135663902,"remaining_time":0.06458670708},
{"learn":[248380.6868],"iteration":917,"passed_time":0.7142211445,"remaining_time":0.06379753142},
{"learn":[248319.7641],"iteration":918,"passed_time":0.7148846431,"remaining_time":0.06300941903},
{"learn":[248253.6589],"iteration":919,"passed_time":0.7155735932,"remaining_time":0.06222379072},
{"learn":[248194.0881],"iteration":920,"passed_time":0.7162359642,"remaining_time":0.06143609248},
{"learn":[248099.9232],"iteration":921,"passed_time":0.7169342639,"remaining_time":0.06065170562},
{"learn":[248081.6027],"iteration":922,"passed_time":0.7175951658,"remaining_time":0.05986438544},
{"learn":[248012.6951],"iteration":923,"passed_time":0.7183005845,"remaining_time":0.05908100045},
{"learn":[248009.2591],"iteration":924,"passed_time":0.7189728668,"remaining_time":0.05829509731},
{"learn":[247958.9294],"iteration":925,"passed_time":0.7197197769,"remaining_time":0.05751540334},
{"learn":[247955.2425],"iteration":926,"passed_time":0.7203254817,"remaining_time":0.05672466037},
{"learn":[247905.616],"iteration":927,"passed_time":0.7210525266,"remaining_time":0.05594373051},
{"learn":[247903.9604],"iteration":928,"passed_time":0.72169293,"remaining_time":0.05515629497},
{"learn":[247872.4575],"iteration":929,"passed_time":0.722366738,"remaining_time":0.05437168996},
{"learn":[247810.3566],"iteration":930,"passed_time":0.7230325325,"remaining_time":0.05358672905},
{"learn":[247806.6308],"iteration":931,"passed_time":0.7236645064,"remaining_time":0.05279955626},
{"learn":[247780.7886],"iteration":932,"passed_time":0.7243823138,"remaining_time":0.05201887998},
{"learn":[247728.5275],"iteration":933,"passed_time":0.7250286481,"remaining_time":0.05123328777},
{"learn":[247648.9738],"iteration":934,"passed_time":0.7257991103,"remaining_time":0.05045662264},
{"learn":[247591.4965],"iteration":935,"passed_time":0.7264939563,"remaining_time":0.04967480043},
{"learn":[247589.7574],"iteration":936,"passed_time":0.7271290533,"remaining_time":0.04888914659},
{"learn":[247481.6607],"iteration":937,"passed_time":0.727825764,"remaining_time":0.04810788632},
{"learn":[247437.9152],"iteration":938,"passed_time":0.7285965361,"remaining_time":0.04733161736},
{"learn":[247421.4179],"iteration":939,"passed_time":0.7292489871,"remaining_time":0.04654780769},
{"learn":[247350.2267],"iteration":940,"passed_time":0.7299423809,"remaining_time":0.04576684429},
{"learn":[247221.034],"iteration":941,"passed_time":0.7306070759,"remaining_time":0.04498429979},
{"learn":[247080.6627],"iteration":942,"passed_time":0.7312541803,"remaining_time":0.04420094197},
{"learn":[247078.0075],"iteration":943,"passed_time":0.731885328,"remaining_time":0.04341692624},
{"learn":[247062.3249],"iteration":944,"passed_time":0.7325332918,"remaining_time":0.04263421275},
{"learn":[247060.9944],"iteration":945,"passed_time":0.7330387967,"remaining_time":0.04184365224},
{"learn":[246990.879],"iteration":946,"passed_time":0.7337573737,"remaining_time":0.04106561859},
{"learn":[246908.473],"iteration":947,"passed_time":0.7347445172,"remaining_time":0.04030244187},
{"learn":[246832.671],"iteration":948,"passed_time":0.7354115902,"remaining_time":0.03952159231},
{"learn":[246794.0736],"iteration":949,"passed_time":0.7361164513,"remaining_time":0.03874297112},
{"learn":[246787.1964],"iteration":950,"passed_time":0.736753057,"remaining_time":0.03796098822},
{"learn":[246771.6301],"iteration":951,"passed_time":0.7374122881,"remaining_time":0.0371804515},
{"learn":[246764.9345],"iteration":952,"passed_time":0.7380367445,"remaining_time":0.03639845435},
{"learn":[246710.402],"iteration":953,"passed_time":0.7387143733,"remaining_time":0.03561935133},
{"learn":[246707.2949],"iteration":954,"passed_time":0.7393514792,"remaining_time":0.03483855138},
{"learn":[246628.433],"iteration":955,"passed_time":0.7400851144,"remaining_time":0.03406249481},
{"learn":[246506.1193],"iteration":956,"passed_time":0.7410491188,"remaining_time":0.03329687786},
{"learn":[246418.2905],"iteration":957,"passed_time":0.7416908983,"remaining_time":0.03251671997},
{"learn":[246361.2423],"iteration":958,"passed_time":0.7423465223,"remaining_time":0.03173744256},
{"learn":[246320.4472],"iteration":959,"passed_time":0.7431281793,"remaining_time":0.03096367414},
{"learn":[246255.2053],"iteration":960,"passed_time":0.7440763752,"remaining_time":0.0301966479},
{"learn":[246179.2517],"iteration":961,"passed_time":0.7447626711,"remaining_time":0.02941889969},
{"learn":[246060.9965],"iteration":962,"passed_time":0.7454280675,"remaining_time":0.02864053842},
{"learn":[245967.2045],"iteration":963,"passed_time":0.7460820388,"remaining_time":0.02786198485},
{"learn":[245945.1603],"iteration":964,"passed_time":0.7467098655,"remaining_time":0.02708274123},
{"learn":[245924.3493],"iteration":965,"passed_time":0.7473667234,"remaining_time":0.02630483291},
{"learn":[245808.7631],"iteration":966,"passed_time":0.7480615818,"remaining_time":0.02552847177},
{"learn":[245693.7891],"iteration":967,"passed_time":0.7487229098,"remaining_time":0.02475117057},
{"learn":[245692.1317],"iteration":968,"passed_time":0.7493425914,"remaining_time":0.0239727764},
{"learn":[245690.5979],"iteration":969,"passed_time":0.7499826732,"remaining_time":0.02319534041},
{"learn":[245643.3017],"iteration":970,"passed_time":0.7506536819,"remaining_time":0.02241911099},
{"learn":[245581.8516],"iteration":971,"passed_time":0.7513064813,"remaining_time":0.02164257354},
{"learn":[245473.5249],"iteration":972,"passed_time":0.7520339321,"remaining_time":0.02086836194},
{"learn":[245429.3515],"iteration":973,"passed_time":0.7527012019,"remaining_time":0.02009263989},
{"learn":[245413.5965],"iteration":974,"passed_time":0.7533734198,"remaining_time":0.01931726717},
{"learn":[245365.1324],"iteration":975,"passed_time":0.7540730935,"remaining_time":0.01854278099},
{"learn":[245350.4187],"iteration":976,"passed_time":0.7548009916,"remaining_time":0.01776911239},
{"learn":[245288.9599],"iteration":977,"passed_time":0.7554787386,"remaining_time":0.01699440925},
{"learn":[245254.7544],"iteration":978,"passed_time":0.7561288222,"remaining_time":0.01621931079},
{"learn":[245232.3095],"iteration":979,"passed_time":0.7567954752,"remaining_time":0.01544480562},
{"learn":[245143.3459],"iteration":980,"passed_time":0.7574575734,"remaining_time":0.0146704321},
{"learn":[245097.1411],"iteration":981,"passed_time":0.758136861,"remaining_time":0.01389660234},
{"learn":[245030.7662],"iteration":982,"passed_time":0.7587851411,"remaining_time":0.01312242869},
{"learn":[244970.9878],"iteration":983,"passed_time":0.7597253772,"remaining_time":0.01235325817},
{"learn":[244955.5511],"iteration":984,"passed_time":0.7605567112,"remaining_time":0.0115820819},
{"learn":[244855.2427],"iteration":985,"passed_time":0.7613115178,"remaining_time":0.01080969701},
{"learn":[244815.5245],"iteration":986,"passed_time":0.7620241841,"remaining_time":0.0100367927},
{"learn":[244684.6792],"iteration":987,"passed_time":0.7627129305,"remaining_time":0.009263719803},
{"learn":[244682.4276],"iteration":988,"passed_time":0.763336468,"remaining_time":0.008490092162},
{"learn":[244645.9731],"iteration":989,"passed_time":0.7641007255,"remaining_time":0.007718189146},
{"learn":[244644.4122],"iteration":990,"passed_time":0.7647563677,"remaining_time":0.006945315145},
{"learn":[244586.6321],"iteration":991,"passed_time":0.7654938914,"remaining_time":0.006173337834},
{"learn":[244536.6198],"iteration":992,"passed_time":0.7661904711,"remaining_time":0.005401141287},
{"learn":[244460.5834],"iteration":993,"passed_time":0.7674060033,"remaining_time":0.004632229396},
{"learn":[244404.6564],"iteration":994,"passed_time":0.7680617219,"remaining_time":0.003859606643},
{"learn":[244367.299],"iteration":995,"passed_time":0.7687112231,"remaining_time":0.003087193667},
{"learn":[244271.2687],"iteration":996,"passed_time":0.7693715624,"remaining_time":0.002315059867},
{"learn":[244233.3431],"iteration":997,"passed_time":0.7700673955,"remaining_time":0.001543221233},
{"learn":[244094.6264],"iteration":998,"passed_time":0.7707671758,"remaining_time":0.0007715387146},
{"learn":[244015.4729],"iteration":999,"passed_time":0.7714229995,"remaining_time":0}
]}